{"ocr_results":[{"text":"八·一三红卫兵","box":[[1200,202],[1594,210],[1593,257],[1199,249]]},{"text":"1967年5月13日","box":[[2294,219],[2552,213],[2553,243],[2295,249]]},{"text":"对抗毛主席革命路线的又一","box":[[378,340],[2191,343],[2191,430],[378,427]]},{"text":"罪行","box":[[2145,340],[2431,335],[2433,415],[2147,420]]},{"text":"一刘奇一九六四年十月七日的一次讲話是不折不扣的三反黑話","box":[[663,462],[2174,468],[2174,520],[663,513]]},{"text":"赴保调查组","box":[[1279,533],[1507,538],[1506,569],[1278,565]]},{"text":"一九六四年在我国城乡开始了轰轰烈烈的伟大的","box":[[265,596],[794,610],[793,645],[264,631]]},{"text":"尖锐地进行着。以毛主席为代表的无产阶级苹命路","box":[[776,608],[1387,616],[1386,646],[776,639]]},{"text":"可忍，敦不可忍！不仅如此，他还要使之流毒全国，","box":[[1369,616],[1973,618],[1973,654],[1368,652]]},{"text":"社会主义教育运动。刘少奇这时追不及待地抛出了他","box":[[215,626],[791,644],[790,678],[214,661]]},{"text":"毛主席指示的又一罪证。","box":[[2006,621],[2275,621],[2275,646],[2006,646]]},{"text":"和刘、邓的资产阶级反动路进行着不可调和的斗","box":[[806,643],[1385,649],[1385,677],[806,670]]},{"text":"的形“左”实右的反动路线与毛主席的无产阶级革命","box":[[214,658],[790,675],[789,710],[213,693]]},{"text":"要“抓住换宁这个材料加批，发到全国。”这是刘少","box":[[1397,651],[1981,652],[1981,684],[1397,683]]},{"text":"争。刘少奇对毛主席的革命路恨之入骨，因此，寻","box":[[807,675],[1385,680],[1385,710],[807,705]]},{"text":"路线分庭抗礼，妄图实现他蓄谋已人的在我国复辟资","box":[[215,691],[790,707],[789,739],[214,723]]},{"text":"奇要一手控制四清运动，要复辟资本主义的罪恶阴谋","box":[[1397,682],[1982,686],[1982,717],[1397,714]]},{"text":"以“蹲点”反调查研究","box":[[2126,683],[2483,678],[2484,717],[2127,722]]},{"text":"找机会发泄他内心的不满。在这次讲话中，他又一次","box":[[803,705],[1379,713],[1379,743],[803,735]]},{"text":"本主义的罪恶阴谋。","box":[[217,723],[426,731],[425,758],[216,750]]},{"text":"的大慕露。","box":[[1401,714],[1516,717],[1515,745],[1400,741]]},{"text":"地发泄出来了，并为他的形“左”实右的反动路寻","box":[[805,735],[1378,743],[1377,775],[804,767]]},{"text":"十月七日李雪峰向他汇报工作时，他的黑讲话就","box":[[263,755],[790,770],[789,802],[262,786]]},{"text":"这里刘少奇还影射我們的伟大领袖毛主席，说什","box":[[1450,749],[1981,751],[1981,778],[1449,776]]},{"text":"“另外一个是要大力蹲点，这是我提的，但是，","box":[[2066,746],[2591,740],[2592,770],[2066,776]]},{"text":"找理论根据。说什么“说我有些偏，主席说过没有重","box":[[805,769],[1378,775],[1377,805],[804,799]]},{"text":"是他反革命罪行的又一个铁证！","box":[[214,786],[550,799],[549,825],[213,812]]},{"text":"么“就是中央也不是那么有成信”，安图毁伟大的毛","box":[[1400,778],[1990,781],[1990,812],[1400,809]]},{"text":"没有人照顾全面也不行，只搞先进大队也不行，我跟","box":[[2005,782],[2606,775],[2607,800],[2005,808]]},{"text":"点就没有政策”，刘少奇竞然拿伟大领袖毛主席的指","box":[[807,800],[1379,806],[1379,837],[807,830]]},{"text":"在讲话中，他疯狂地攻击我们的伟大领袖毛主席","box":[[263,818],[787,831],[786,862],[262,850]]},{"text":"泽东思想。真是“此蚂大树，可笑不自量。”","box":[[1399,809],[1925,811],[1925,843],[1398,841]]},{"text":"彭真同志讲了，我要控制一百人左右作为预备队，发","box":[[2003,811],[2608,805],[2608,835],[2003,841]]},{"text":"示作为反动路的挡箭牌，真是恶毒到极点了！","box":[[805,832],[1318,838],[1317,868],[804,862]]},{"text":"和战无不胜的毛泽东思想。不遗余力地鼓吹他形“左”","box":[[212,847],[785,861],[784,897],[211,883]]},{"text":"毛主席教导我們说：“共产党員对于在工作中犯","box":[[1453,844],[1984,847],[1984,874],[1452,871]]},{"text":"现那个地委不行，就派他们去搞，这一百人都是司、","box":[[2003,846],[2591,839],[2592,865],[2003,871]]},{"text":"1962年，无是在七千人大会上，还是在东北、","box":[[854,864],[1364,870],[1364,900],[854,894]]},{"text":"实右的反动路线。用“打击一大片，保护一小”来，","box":[[212,880],[818,896],[817,927],[211,912]]},{"text":"过錯的人们，除了不可救药者外，不是朵取排斥","box":[[1402,876],[1982,879],[1982,906],[1401,903]]},{"text":"局长也不一定都行，可在那个点上调好的来，把他们","box":[[2005,877],[2608,871],[2608,897],[2005,903]]},{"text":"华北的讲话，他根本不是什么反“左”，而是反对三","box":[[803,894],[1378,902],[1377,932],[803,924]]},{"text":"抵制毛主席的关于干部问题的正确政策。","box":[[214,913],[647,927],[646,953],[213,939]]},{"text":"态度，而是朵取规劝态度，使之翻然改进，弃旧图","box":[[1397,906],[1982,909],[1982,939],[1397,936]]},{"text":"留下搞。对省委、地委、县委好的同志和较好的同志","box":[[2002,908],[2609,901],[2610,932],[2002,938]]},{"text":"面红旗、反对党的方针政策。","box":[[809,929],[1119,932],[1119,959],[809,956]]},{"text":"他大肆反对毛主席的群众路线的正确方针，用他","box":[[262,943],[785,956],[784,991],[261,978]]},{"text":"新。”而刘少奇这个党内最大的走资本主义道路的当","box":[[1399,936],[1979,941],[1979,971],[1398,966]]},{"text":"要帮助，不行的就换，予备队的人也不行，就从下边","box":[[2003,939],[2608,935],[2608,965],[2003,970]]},{"text":"1964年，他根本不是什么“反右”而是反对“前","box":[[853,957],[1378,965],[1377,995],[852,987]]},{"text":"的所谓“蹲点”、“火候”来反对放手发动群众。","box":[[212,974],[721,989],[720,1020],[211,1004]]},{"text":"权派，竞然说什么“开除不怕多，开除了才能挽救","box":[[1399,968],[1982,973],[1982,1003],[1398,998]]},{"text":"点上调一个人上来。我控制一百人准备联系抚宁。”","box":[[2005,971],[2599,963],[2599,995],[2005,1003]]},{"text":"十条”、“二十三条”，反对伟大的社会主义教育运","box":[[803,984],[1381,994],[1380,1029],[803,1019]]},{"text":"总之，这篇黑讲话是他形“左”实右反动路线的","box":[[263,1007],[784,1019],[783,1051],[262,1039]]},{"text":"他，他才能真正改，开除了多少是多少。”把苹命","box":[[1396,1001],[1979,1004],[1979,1034],[1395,1031]]},{"text":"按：刘少奇在他一手泡制的“后十条”中就十分","box":[[2054,1006],[2606,1001],[2607,1027],[2054,1031]]},{"text":"动。","box":[[803,1025],[843,1025],[843,1048],[803,1048]]},{"text":"一篇活教材。","box":[[223,1039],[353,1044],[352,1069],[222,1064]]},{"text":"干部打成右派，要把所有的好党员完全开除。他这样","box":[[1402,1033],[1982,1036],[1982,1066],[1401,1063]]},{"text":"卖力地强调他的所谓“蹲点”，用之来反对毛主席关","box":[[2006,1036],[2608,1034],[2608,1062],[2006,1063]]},{"text":"归根结底一句话，他反对毛主席、反对伟大的毛","box":[[856,1052],[1376,1062],[1376,1092],[855,1083]]},{"text":"下面摘录几段，让我们用伟大的战无不胜的毛泽，","box":[[265,1070],[793,1083],[792,1113],[264,1101]]},{"text":"不遗余力地打击一大片，其目的就是要保护那么一小","box":[[1402,1066],[1984,1069],[1984,1096],[1401,1093]]},{"text":"·","box":[[1982,1074],[2012,1074],[2012,1086],[1982,1086]]},{"text":"于调查研究的最高指示。在这里他又别有用心地把这","box":[[2005,1068],[2608,1068],[2608,1093],[2005,1093]]},{"text":"泽东思想。","box":[[803,1085],[928,1089],[927,1115],[803,1111]]},{"text":"东思想这个照妖镜来照一照这又黑又毒的讲话吧！","box":[[211,1101],[743,1115],[742,1145],[210,1131]]},{"text":"摆走资本主义道路的当权派。","box":[[1400,1098],[1714,1101],[1713,1127],[1400,1123]]},{"text":"个臭货抛了出来，并且还恬不知耻地说：“大力蹲","box":[[2005,1099],[2608,1098],[2608,1125],[2005,1126]]},{"text":"五年前的那“一股风”，就是刘少奇为帝国主义、","box":[[851,1114],[1361,1122],[1361,1154],[851,1146]]},{"text":"点，这是我提的。”真是不打自招。须指出的是，刘少","box":[[2009,1133],[2605,1133],[2605,1158],[2009,1158]]},{"text":"修正主义效劳，替右倾机会主义分子明冤翻素的黑风，","box":[[805,1149],[1370,1158],[1370,1186],[804,1176]]},{"text":"反对毛主席的群众路线","box":[[316,1161],[685,1172],[684,1208],[315,1197]]},{"text":"借反教条主义，攻击毛主席","box":[[1463,1161],[1913,1166],[1913,1204],[1463,1199]]},{"text":"奇的所蹲点和二十三条中提的蹲点是有着本质的不","box":[[2008,1164],[2608,1164],[2608,1190],[2008,1190]]},{"text":"三年前的那股“邪气”就是刘少奇形“左”实右，破坏","box":[[806,1179],[1376,1189],[1376,1219],[806,1209]]},{"text":"同。“二十三条”中提出的蹲点，首先是“没有调查就","box":[[2005,1194],[2609,1196],[2609,1223],[2005,1222]]},{"text":"伟大四济运动的邪气。“联系1962年的右倾和1964年","box":[[805,1209],[1378,1220],[1377,1250],[804,1240]]},{"text":"“现在下边有个说法，越往下边越接近真理，这","box":[[269,1220],[785,1232],[784,1263],[268,1250]]},{"text":"在李雪峰讲到×××的一些情况时，刘少奇说：","box":[[1450,1225],[1964,1228],[1964,1253],[1449,1250]]},{"text":"没有发言权”，“过去我們党采用的开調查会等行","box":[[2003,1226],[2611,1226],[2611,1256],[2003,1256]]},{"text":"形‘左”实右的錯向，不是可以令人深省？”","box":[[802,1241],[1364,1252],[1364,1282],[801,1271]]},{"text":"话不对，说越往下越接近真理，就是不接近群众，中","box":[[209,1252],[785,1266],[784,1294],[208,1280]]},{"text":"“他断了，大概他以为只有他最了解情况，和江滑","box":[[1414,1258],[1985,1259],[1985,1287],[1413,1285]]},{"text":"之有效的調查研究方法，应当继续采用。”而刘少寺","box":[[2003,1258],[2609,1258],[2609,1288],[2003,1288]]},{"text":"央还不是听你们的，你们华北也一样。”","box":[[206,1282],[654,1290],[654,1324],[205,1317]]},{"text":"毛主席的这段话就是对刘少奇的判决！","box":[[802,1273],[1217,1282],[1216,1312],[801,1303]]},{"text":"清一样，就是要刺他。我在南京讲了五次话，他写了","box":[[1397,1286],[1981,1291],[1981,1321],[1397,1317]]},{"text":"的所谓蹲点，闲口不谈调查研究，只一味要“各级的","box":[[2002,1290],[2612,1291],[2612,1321],[2002,1320]]},{"text":"那么个报告，问题不在于能不能往下批发他那个报","box":[[1399,1318],[1981,1323],[1981,1353],[1398,1348]]},{"text":"主要领导人员，都必须亲自蹲点，以便取得经验，做","box":[[2005,1324],[2611,1327],[2611,1353],[2005,1350]]},{"text":"按：毛主席教导我們：“我們应該走到群众中間","box":[[257,1335],[781,1349],[780,1374],[256,1360]]},{"text":"打击一大片，保护一小撮","box":[[883,1338],[1295,1347],[1294,1388],[882,1378]]},{"text":"告，报告里讲的话都不错，就是犯了教条主义的错","box":[[1399,1350],[1982,1355],[1982,1385],[1398,1380]]},{"text":"出样子，指导和带动全县运动”，要“真正蹲下去”。","box":[[2003,1353],[2597,1356],[2597,1386],[2003,1383]]},{"text":"去，向群众学习。”“在我党的一切实际工作中，凡","box":[[208,1363],[784,1377],[783,1408],[207,1394]]},{"text":"误，我说官坐得越久，官坐得越高，真理越少，这样","box":[[1399,1382],[1984,1386],[1984,1416],[1398,1412]]},{"text":"属正确的领导，必须是从群众中来，到群众中去。”","box":[[205,1392],[782,1401],[781,1442],[204,1433]]},{"text":"表面看是要深入群众，实际上这里面包藏肴一颗不可","box":[[2003,1388],[2610,1392],[2609,1418],[2003,1413]]},{"text":"在李雪峰讲到太、石会议情况时，刘少奇讲：","box":[[851,1401],[1360,1410],[1359,1439],[851,1430]]},{"text":"你就不可能不在基层干部影响下盲目行动，有什么英","box":[[1397,1415],[1982,1421],[1982,1447],[1397,1440]]},{"text":"在这里刘少奇公然对抗毛主席关于群众路的最高指","box":[[208,1428],[784,1444],[783,1469],[207,1454]]},{"text":"告人的祸心。说穿了就是对抗毛主席调查研究的方法。","box":[[2005,1419],[2607,1426],[2606,1451],[2005,1445]]},{"text":"“抚宁县委开会讨论桃园大队吴臣的问题时，有各种","box":[[817,1431],[1378,1442],[1377,1474],[816,1463]]},{"text":"明呢？你们华北局也在内。”","box":[[1397,1443],[1715,1447],[1715,1477],[1397,1474]]},{"text":"示，害怕群众，反对群众，更害怕领导干部深入下去","box":[[209,1460],[782,1474],[781,1501],[208,1487]]},{"text":"毛主席：“各种削阶级的代表人物…他們","box":[[2054,1451],[2611,1456],[2611,1486],[2054,1481]]},{"text":"意见（王光美：有些意见很好玩），一次地委派组织部","box":[[806,1466],[1376,1475],[1376,1503],[806,1493]]},{"text":"按：刘少奇在这里又一次迫不及待地说“官坐得","box":[[1445,1478],[1979,1483],[1979,1509],[1445,1504]]},{"text":"与群众相结合。胡说“越往下越接近真理，就是不接","box":[[209,1490],[785,1503],[784,1533],[208,1520]]},{"text":"老是在研究对付我們的策略，‘窥测方向’，以求一。”","box":[[2000,1481],[2610,1486],[2609,1518],[2000,1513]]},{"text":"监委去检查。一次省委派了一个处长去审批，省委派","box":[[808,1498],[1378,1507],[1377,1534],[807,1525]]},{"text":"越久，官坐得越高，真理越少”这些黑话在给江消清","box":[[1390,1507],[1981,1513],[1981,1543],[1389,1537]]},{"text":"近群众”。故意把真理和群众对立起来。这实际上就","box":[[206,1520],[785,1536],[784,1566],[205,1551]]},{"text":"党内最大的一小摄走资本主义道路的当权派刘少奇、","box":[[2005,1516],[2596,1522],[2596,1549],[2005,1543]]},{"text":"这么一个人去，威信就降低了。要规定凡是没有参加","box":[[808,1528],[1405,1539],[1404,1566],[807,1555]]},{"text":"的一封信中就反复强调过。这里又重新抛了出米，其","box":[[1391,1540],[1979,1546],[1979,1574],[1391,1567]]},{"text":"是打着“接近群众”的悦子，米贩卖他的打击和迫害","box":[[206,1552],[785,1568],[784,1598],[205,1582]]},{"text":"邓小平、彭真之流，看中了这場四清运动，企图一手","box":[[2003,1546],[2610,1555],[2609,1583],[2003,1573]]},{"text":"过四清的就没有审批资格，这至少要看一年，四清蹲","box":[[806,1558],[1379,1568],[1379,1598],[806,1588]]},{"text":"目的不是很明显了吗？江消清的讲话引了前10条和毛","box":[[1397,1572],[1982,1580],[1982,1605],[1397,1597]]},{"text":"群众的黑货。","box":[[206,1585],[347,1589],[346,1616],[205,1613]]},{"text":"控制，把运动引向斜路。他们要纠集兵力，把桃园变","box":[[2002,1579],[2608,1589],[2608,1614],[2002,1605]]},{"text":"点工作作好了，才能审批，现在审批没有“左”的，都","box":[[809,1591],[1378,1601],[1377,1628],[809,1619]]},{"text":"主席的许多教导，刘少奇批部他犯了教条主义的","box":[[1397,1604],[1985,1611],[1985,1637],[1397,1629]]},{"text":"刘少奇在64年9月30日给江渭清的一封信中，就","box":[[255,1617],[785,1628],[784,1658],[255,1647]]},{"text":"成推行反动路，把杀四清运动的一个基地。","box":[[2002,1608],[2535,1619],[2534,1649],[2002,1638]]},{"text":"是右的。都是减轻的，没有加重的。越审批越右，干脆","box":[[808,1622],[1378,1632],[1377,1660],[807,1649]]},{"text":"误，目的何在呢？毛主席：“修正主义者，右倾机","box":[[1391,1631],[1981,1642],[1980,1673],[1391,1662]]},{"text":"曾猖狂地叫喊“官越大，真理越少，官做得越大，真理","box":[[207,1647],[784,1660],[783,1690],[207,1677]]},{"text":"不审啦。我打算抓住抚宁这个材料加批，发到全国。”","box":[[808,1653],[1379,1664],[1379,1691],[807,1681]]},{"text":"会主义者，口头上也挂着马思主义，他們也在那里","box":[[1396,1667],[1979,1675],[1979,1700],[1395,1693]]},{"text":"以“火候”反对","box":[[2163,1662],[2443,1669],[2442,1710],[2162,1703]]},{"text":"也就越少。”时隔不到10天，就又说什么“越往下边","box":[[203,1677],[784,1691],[783,1722],[202,1708]]},{"text":"当华北局负责人说到：“工作队到了一定时候亮","box":[[856,1683],[1379,1693],[1379,1723],[855,1714]]},{"text":"攻击‘教条主义”。但是他們所攻击的正是马克思主义","box":[[1394,1696],[1981,1706],[1980,1734],[1394,1723]]},{"text":"越接近真理，这话不对”，说穿了就是说上面（按：","box":[[203,1709],[769,1723],[768,1753],[202,1739]]},{"text":"牌子，太原化肥厂就是工人向中央工作组告状以后发","box":[[808,1717],[1378,1726],[1377,1753],[807,1744]]},{"text":"“放手发动群众”","box":[[2170,1715],[2437,1720],[2436,1761],[2170,1756]]},{"text":"的最根本的东西。”刘少奇极力攻击“教条主义”。但","box":[[1394,1729],[1981,1738],[1980,1764],[1394,1755]]},{"text":"指毛主席）没有真理，真是狂妄到极点，刘少奇口口","box":[[201,1742],[781,1755],[780,1784],[201,1771]]},{"text":"现的。”","box":[[805,1749],[902,1744],[904,1771],[807,1776]]},{"text":"是他所攻击的实质是攻击毛泽东思想的灵魂，安图間","box":[[1399,1761],[1979,1771],[1979,1797],[1398,1786]]},{"text":"声声地叫什么所谓“真理”。其目的就是含沙射影","box":[[204,1774],[782,1787],[781,1815],[204,1803]]},{"text":"“x××同志观点改变了，我听了很高兴，xx","box":[[2062,1765],[2608,1782],[2607,1817],[2061,1800]]},{"text":"刘讲：“看来，中央还有点威信，省委也有点威","box":[[853,1776],[1376,1785],[1376,1817],[852,1807]]},{"text":"割毛泽东思想最本质的的东西。","box":[[1397,1791],[1738,1799],[1737,1824],[1397,1816]]},{"text":"地攻击我們伟大的领袖毛主席。","box":[[203,1807],[549,1815],[549,1841],[202,1833]]},{"text":"信，、象河北派那样一个处长去审批，威信不是一下子","box":[[806,1809],[1373,1820],[1373,1847],[806,1836]]},{"text":"同志很聪明，我给江渭清的信，可以给第一书记看，","box":[[2005,1803],[2596,1817],[2596,1844],[2005,1830]]},{"text":"李雪峰讲到当前干部精神状态，要提反右倾口号，","box":[[1448,1824],[2008,1836],[2007,1862],[1448,1850]]},{"text":"战无不胜的毛泽东思想是颠扑不破的伟大、光辉","box":[[254,1839],[782,1851],[781,1877],[253,1865]]},{"text":"就完了！就是中央也不是那么有威信，有那么多人写","box":[[806,1841],[1376,1851],[1376,1877],[806,1866]]},{"text":"地、县不要发了。信的内容可用你们的话往下讲，等","box":[[1999,1834],[2610,1848],[2609,1876],[1999,1862]]},{"text":"方法当然要研究，河北反中游搞了四十多天还不行。","box":[[1393,1851],[1978,1865],[1977,1895],[1392,1881]]},{"text":"的真理。亿万人民群众就是在伟大的毛泽东思想的指","box":[[204,1868],[782,1880],[781,1910],[204,1898]]},{"text":"匿名信，还不是说那个地方有打击报复。太原化肥厂","box":[[805,1872],[1361,1883],[1361,1909],[804,1898]]},{"text":"江渭清的信来了再说，……·现在要想一想，运动展开","box":[[2001,1865],[2613,1880],[2612,1910],[2000,1895]]},{"text":"刘少奇说：“好，我赞成，就将你讲的写个简单","box":[[1448,1886],[1982,1900],[1982,1927],[1448,1913]]},{"text":"导下前进。刘少奇这样狂犬吹日的结果，只能是自取","box":[[207,1899],[782,1910],[781,1938],[207,1927]]},{"text":"那个打报复的人只速捕不够，要开除党籍，开除子","box":[[809,1901],[1378,1913],[1377,1939],[809,1927]]},{"text":"后，如何掌握面的问题，整个过程都有个火候问题，","box":[[1998,1898],[2590,1912],[2589,1942],[1997,1928]]},{"text":"报告、我批、通报全国，我最近忙干接待外宾，顾不","box":[[1397,1916],[1984,1930],[1983,1956],[1397,1942]]},{"text":"灭亡","box":[[207,1932],[269,1938],[267,1961],[205,1955]]},{"text":"将来表现好了再吸收嘛，开除不怕多，开除了才能挽","box":[[803,1931],[1375,1942],[1374,1972],[803,1961]]},{"text":"一个大队，一个县一个省，华北局全国都有个火候间","box":[[2001,1926],[2608,1944],[2607,1974],[2000,1957]]},{"text":"上，不人，我就要抓，我看四清，公社一级不能领","box":[[1397,1946],[1984,1960],[1983,1987],[1397,1973]]},{"text":"救他，他才能真正改错。开除多少是多少，该开除的","box":[[803,1961],[1375,1972],[1374,2004],[803,1993]]},{"text":"题。全国的我们掌握，你们的你们要掌握，出了事要","box":[[2002,1960],[2611,1977],[2610,2007],[2001,1990]]},{"text":"导，县委也不行，有些地委也不行，有的省委，如贵","box":[[1393,1976],[1986,1993],[1985,2022],[1392,2005]]},{"text":"肆意歪曲毛澤东思想","box":[[320,1991],[660,1998],[660,2034],[319,2028]]},{"text":"就开除，我看五反与市、区都有关系，当然不是全","box":[[803,1993],[1378,2006],[1377,2036],[803,2023]]},{"text":"亲自去，连系一个大队，一个县就够了，连系不要","box":[[2002,1991],[2613,2010],[2612,2040],[2001,2022]]},{"text":"州也不行，省也要帮助。”","box":[[1396,2010],[1688,2016],[1688,2043],[1395,2037]]},{"text":"部，总是区、市中有人。”","box":[[803,2025],[1097,2026],[1097,2058],[803,2057]]},{"text":"多，我只与王光美那里连系一个大队，她个把月回来","box":[[2005,2025],[2611,2042],[2610,2072],[2004,2055]]},{"text":"“说我有些偏，主席说过没有重点就没有政策，","box":[[268,2041],[766,2054],[765,2086],[267,2073]]},{"text":"按：一谈到反右倾，刘少奇就欣然同意，并馬上","box":[[1444,2041],[1987,2055],[1986,2086],[1443,2072]]},{"text":"按：这又是刘少奇形“左”实右的又一铁证！刘","box":[[848,2056],[1376,2066],[1376,2098],[848,2088]]},{"text":"汇报一次，其实我也没有多说话，现在打算连系一个","box":[[2001,2056],[2610,2075],[2609,2105],[2000,2087]]},{"text":"我这个人也反过“左”，也反过右，如七千人大会上还","box":[[206,2075],[782,2086],[781,2116],[205,2105]]},{"text":"要亲自批发全国。这是为什么呢？明眼人一看就明","box":[[1396,2071],[1987,2087],[1986,2117],[1395,2102]]},{"text":"福","box":[[1984,2066],[2000,2066],[2000,2076],[1984,2076]]},{"text":"少奇为了达到他“打击一大片、保护一小报”的险","box":[[799,2087],[1378,2101],[1377,2131],[798,2117]]},{"text":"县，了解她整个过程怎么搞的，……反右非反不行，","box":[[2001,2085],[2596,2105],[2595,2140],[2000,2120]]},{"text":"不是反“左？反了以后又出了大问题，就起了一股","box":[[207,2109],[780,2119],[780,2144],[207,2135]]},{"text":"白，刘少奇是为了保护他的形“左”实右的反动路","box":[[1396,2103],[1987,2120],[1986,2151],[1395,2133]]},{"text":"恶目的，竞然违反党的监察原则。什么“一律不审","box":[[800,2118],[1378,2131],[1377,2161],[800,2149]]},{"text":"怕‘左’反右要反二年，反右当中防‘左’，如提出火候","box":[[1999,2120],[2614,2140],[2613,2170],[1998,2150]]},{"text":"风，可大哩。我反‘左”时×××就赞成，劲头来了.","box":[[204,2138],[774,2149],[774,2179],[204,2168]]},{"text":"，安图以反右倾来达到这个目的。","box":[[1395,2136],[1793,2149],[1793,2175],[1394,2162]]},{"text":"批，要批只能加重。”这是典型的形“左”实右。省","box":[[800,2148],[1375,2166],[1374,2196],[799,2179]]},{"text":"问题，两个百分之九十五。运动后期再作组织处理，","box":[[2002,2153],[2596,2173],[2595,2203],[2001,2183]]},{"text":"我一反右他就不干了。反‘左”以后，邪气也来了，他","box":[[204,2171],[780,2181],[780,2208],[204,2198]]},{"text":"如对待干部的問题上，二十三条明确指出有如下","box":[[1448,2170],[1979,2184],[1979,2211],[1448,2197]]},{"text":"委一次派一个干部去桃国实市求是地审查素件，触怒","box":[[799,2180],[1378,2197],[1377,2228],[798,2210]]},{"text":"县烂了倒好办，烂了就照信阳的办法办，组织一批人","box":[[2001,2185],[2607,2205],[2606,2235],[2000,2215]]},{"text":"就积极讲了那么一套。看你强调什么，一个时候强调","box":[[204,2201],[782,2211],[781,2241],[204,2232]]},{"text":"四种：“好的、比较好的、問题的性质比较严重的………","box":[[1390,2200],[1981,2217],[1980,2246],[1389,2229]]},{"text":"了王光美。刘少奇就认为监察委员会各级都右。因此","box":[[803,2213],[1381,2229],[1380,2258],[803,2242]]},{"text":"去夺权，把原来的人集训。","box":[[2002,2219],[2302,2229],[2301,2256],[2001,2247]]},{"text":"什么，如两面都强调，那不是等于什么都强调。”","box":[[203,2235],[746,2243],[746,2271],[202,2263]]},{"text":"在一般情况下，前两种人是多数。”而刘少奇却说：“我","box":[[1365,2230],[1980,2247],[1979,2277],[1364,2260]]},{"text":"他规定凡是四清案件，一律不能由监委插手。乱发号看四清，公社一级不能领导，县委也不行，有些地委","box":[[800,2244],[1980,2280],[1979,2311],[799,2274]]},{"text":"总之，凡烂了的调开再说，调开好发动群众，等","box":[[2052,2250],[2608,2270],[2607,2300],[2051,2280]]},{"text":"按：解放十七年来党内两条路的斗争仍然是在","box":[[252,2265],[786,2274],[786,2304],[252,2295]]},{"text":"施令，依使他的特权地位，任意践踏党的原则，是也不行，有的省要如贵州也不行。”这是公开反对","box":[[770,2275],[1981,2312],[1980,2342],[769,2306]]},{"text":"群众翻了身，群众起来了，你说有问题再回去，支书","box":[[1999,2281],[2608,2303],[2607,2333],[1998,2311]]},{"text":"也可以外边派去嘛。总之在我们专政条件下搞革命，","box":[[2000,2311],[2593,2336],[2592,2368],[1998,2343]]},{"text":"解放后刘奇在天津活动情况簡表","box":[[667,2325],[1498,2352],[1497,2398],[666,2372]]},{"text":"总是好革。凡是烂了的，一律采取信阳的办法，又有","box":[[2001,2345],[2608,2370],[2607,2400],[2000,2375]]},{"text":"（天津调查组制表）","box":[[1683,2376],[1891,2385],[1890,2416],[1682,2408]]},{"text":"效，又好搞。”","box":[[1999,2377],[2173,2380],[2172,2412],[1999,2408]]},{"text":"时","box":[[228,2405],[252,2405],[252,2424],[228,2424]]},{"text":"间","box":[[321,2405],[345,2405],[345,2424],[321,2424]]},{"text":"活","box":[[410,2407],[441,2407],[441,2428],[410,2428]]},{"text":"动","box":[[659,2407],[681,2407],[681,2430],[659,2430]]},{"text":"陪同人和参加人","box":[[761,2408],[934,2413],[933,2439],[761,2434]]},{"text":"备","box":[[983,2418],[1004,2418],[1004,2439],[983,2439]]},{"text":"注","box":[[1028,2418],[1058,2418],[1058,2442],[1028,2442]]},{"text":"时","box":[[1107,2419],[1134,2419],[1134,2445],[1107,2445]]},{"text":"按：这里刘少奇又反复强调王光美的“桃园經","box":[[2048,2410],[2605,2433],[2604,2463],[2046,2440]]},{"text":"间","box":[[1200,2422],[1232,2422],[1232,2448],[1200,2448]]},{"text":"活","box":[[1301,2430],[1323,2430],[1323,2451],[1301,2451]]},{"text":"陪同人和参加人","box":[[1651,2435],[1825,2440],[1824,2468],[1650,2463]]},{"text":"备","box":[[1874,2445],[1897,2445],[1897,2467],[1874,2467]]},{"text":"验”中的“火候”。用运动中掌握“火候”来反对毛主","box":[[1997,2438],[2604,2466],[2603,2496],[1995,2468]]},{"text":"1949年","box":[[215,2451],[282,2451],[282,2478],[215,2478]]},{"text":"4月18日发表对天津工作的初步意见","box":[[278,2448],[603,2454],[603,2484],[277,2478]]},{"text":"注","box":[[1930,2451],[1951,2451],[1951,2469],[1930,2469]]},{"text":"住原台湾路","box":[[970,2464],[1067,2468],[1066,2495],[969,2491]]},{"text":"1958年","box":[[1100,2469],[1170,2469],[1170,2496],[1100,2496]]},{"text":"7月20日","box":[[1163,2472],[1247,2472],[1247,2499],[1163,2499]]},{"text":"由天津到济南等地视察后又返回天津停留","box":[[1257,2473],[1595,2486],[1594,2513],[1256,2500]]},{"text":"席的关于放手发动群众的指示。并且还说什么“一个","box":[[2000,2473],[2604,2498],[2603,2528],[1998,2503]]},{"text":"4月21日","box":[[287,2493],[374,2493],[374,2519],[287,2519]]},{"text":"在东亚毛纺厂，上午与臭资本家宋渠卿密谈，","box":[[368,2493],[726,2498],[726,2523],[368,2519]]},{"text":"7号","box":[[974,2489],[1013,2489],[1013,2511],[974,2511]]},{"text":"至","box":[[1185,2495],[1230,2495],[1230,2517],[1185,2517]]},{"text":"7月21日","box":[[1173,2511],[1246,2514],[1245,2537],[1172,2533]]},{"text":"大队，一个县一个省华北局、全国都有“火候”問题”，","box":[[2000,2505],[2587,2531],[2586,2560],[1998,2533]]},{"text":"下午在工人的强烈要求下，才与工人见面和","box":[[371,2516],[728,2520],[728,2541],[371,2537]]},{"text":"工人开了一个座谈会","box":[[371,2534],[546,2537],[546,2560],[370,2556]]},{"text":"1960年","box":[[1102,2545],[1162,2551],[1160,2578],[1099,2572]]},{"text":"其目的就是要在全国范围内，把轰轰烈烈的群众运动","box":[[1998,2536],[2602,2564],[2601,2595],[1997,2567]]},{"text":"3月24日参加中央召开的天津会议","box":[[1162,2550],[1465,2561],[1464,2588],[1161,2577]]},{"text":"4月24日","box":[[287,2573],[368,2573],[368,2599],[287,2599]]},{"text":"提出对天津工作的指示","box":[[368,2573],[564,2576],[564,2602],[367,2599]]},{"text":"住院南道招","box":[[1860,2573],[1962,2578],[1960,2604],[1859,2598]]},{"text":"打下去，为更好地实行他的“打击一大片，保护一小","box":[[1995,2568],[2601,2596],[2600,2626],[1994,2598]]},{"text":"3月26日","box":[[1171,2591],[1246,2595],[1245,2622],[1170,2618]]},{"text":"一、参观天津自行车厂","box":[[1256,2596],[1442,2599],[1442,2626],[1256,2623]]},{"text":"王光美和他两个小孩同","box":[[1630,2604],[1844,2611],[1844,2641],[1629,2635]]},{"text":"待所","box":[[1861,2596],[1904,2596],[1904,2618],[1861,2618]]},{"text":"操”，为控制全国的四清运动，使伟大的四清运动走","box":[[1997,2600],[2599,2629],[2598,2660],[1995,2630]]},{"text":"4月25日","box":[[288,2615],[360,2615],[360,2638],[288,2638]]},{"text":"接见了“工商业家上层人士”（在现政","box":[[396,2612],[728,2619],[727,2646],[396,2639]]},{"text":"参观天津钢厂第一分厂","box":[[1291,2618],[1481,2625],[1481,2646],[1290,2639]]},{"text":"协礼堂）","box":[[408,2636],[480,2636],[480,2658],[408,2658]]},{"text":"三","box":[[1259,2630],[1302,2634],[1299,2657],[1257,2652]]},{"text":"参观津塘路木材厂","box":[[1291,2638],[1441,2641],[1440,2662],[1290,2659]]},{"text":"米，由林铁、刘子厚、万晓","box":[[1630,2635],[1841,2643],[1840,2670],[1629,2662]]},{"text":"入岐途。他不是声称要“全国我們学握”吗？行且刘","box":[[1998,2631],[2602,2661],[2601,2691],[1997,2662]]},{"text":"在各公营工厂职员会议上讲话（在原跃","box":[[402,2651],[729,2658],[729,2683],[402,2677]]},{"text":"四、参观天津市针织研究所","box":[[1254,2651],[1481,2661],[1480,2687],[1253,2677]]},{"text":"塘、祖荣汉等陪同","box":[[1631,2662],[1780,2670],[1779,2697],[1629,2689]]},{"text":"少奇还死死抓住桃因这个大队不放。“我只与王光美","box":[[1997,2663],[2604,2694],[2602,2725],[1995,2693]]},{"text":"华中学现十六中）","box":[[406,2673],[555,2676],[555,2702],[405,2698]]},{"text":"3月27日","box":[[1172,2692],[1244,2692],[1244,2713],[1172,2713]]},{"text":"二、参观西货场","box":[[1256,2694],[1391,2695],[1391,2721],[1256,2719]]},{"text":"王光美和他两个小孩同","box":[[1630,2704],[1842,2714],[1840,2741],[1629,2731]]},{"text":"那里連系一个大队”，为他复辟资本主义寻找根据","box":[[1995,2695],[2602,2726],[2601,2756],[1994,2725]]},{"text":"4月28日","box":[[288,2713],[360,2713],[360,2736],[288,2736]]},{"text":"参加天津市第一届职工代表会议，并作了报告","box":[[369,2713],[734,2718],[734,2742],[369,2738]]},{"text":"二、参观原兴安路人民公社的巨龙拔丝模","box":[[1260,2712],[1613,2724],[1612,2750],[1259,2737]]},{"text":"厂，托儿所，食堂","box":[[1293,2733],[1445,2739],[1444,2761],[1292,2754]]},{"text":"来，由林铁、刘子厚、万","box":[[1629,2731],[1843,2743],[1842,2770],[1628,2758]]},{"text":"地，建立桥头堡。","box":[[1995,2728],[2202,2740],[2200,2767],[1994,2755]]},{"text":"4月30日","box":[[288,2754],[359,2754],[359,2777],[288,2777]]},{"text":"刘少奇接到宋卿的来信（在天津）","box":[[369,2754],[662,2757],[662,2783],[369,2780]]},{"text":"三、参观郑庄子主食加工站","box":[[1257,2751],[1490,2761],[1489,2782],[1256,2772]]},{"text":"四、参观大中华橡胶厂（现橡胶一厂）","box":[[1255,2769],[1562,2779],[1562,2804],[1254,2795]]},{"text":"晓塘、张淮三等陪同","box":[[1630,2761],[1804,2770],[1803,2797],[1629,2789]]},{"text":"对于基层烂了的红藏，刘少奇主张调开再说，他","box":[[2045,2760],[2601,2791],[2599,2823],[2043,2791]]},{"text":"5月3日","box":[[288,2797],[359,2797],[359,2819],[288,2819]]},{"text":"说这样好发动群众。什么“好发动群众”！纯粹是为","box":[[1995,2788],[2601,2824],[2599,2856],[1994,2820]]},{"text":"刘少奇回宋装卿信一封（在天津）","box":[[371,2798],[644,2798],[644,2824],[371,2824]]},{"text":"3月28日","box":[[1172,2802],[1246,2808],[1244,2835],[1170,2829]]},{"text":"一、听取省委、市委负责人的汇报","box":[[1255,2808],[1537,2818],[1536,2845],[1254,2836]]},{"text":"二、接见河北省委召开的六级干部会议千","box":[[1260,2828],[1610,2842],[1609,2868],[1259,2854]]},{"text":"了保护一小报！把所有干部调开了，一小撮走资本主","box":[[1997,2823],[2598,2857],[2596,2888],[1995,2853]]},{"text":"5月5日","box":[[288,2837],[359,2837],[359,2860],[288,2860]]},{"text":"参加华北职工代表会议，井作了报告","box":[[369,2837],[672,2840],[672,2866],[369,2863]]},{"text":"部","box":[[1289,2852],[1314,2852],[1314,2872],[1289,2872]]},{"text":"义道路的当权派和牛鬼蛇神便可以保护起来，那些好","box":[[1995,2853],[2601,2889],[2599,2919],[1994,2884]]},{"text":"5月6日","box":[[288,2878],[359,2878],[359,2901],[288,2901]]},{"text":"一、参加天津市委扩大会议，并作了指示","box":[[369,2878],[711,2880],[711,2905],[369,2904]]},{"text":"1962年","box":[[1098,2884],[1158,2884],[1158,2907],[1098,2907]]},{"text":"春","box":[[1196,2887],[1217,2887],[1217,2908],[1196,2908]]},{"text":"来天津医治胳骨","box":[[1253,2885],[1389,2894],[1387,2921],[1251,2912]]},{"text":"的和比较好的干部便不能与群众一起揭发和斗争一小","box":[[1995,2887],[2598,2922],[2596,2951],[1994,2915]]},{"text":"参加天津市干部会，并对提出的问题作","box":[[401,2898],[726,2899],[726,2925],[401,2923]]},{"text":"王光美及其秘书同来，林","box":[[1630,2902],[1841,2910],[1840,2937],[1629,2929]]},{"text":"了解答","box":[[410,2919],[470,2919],[470,2942],[410,2942]]},{"text":"住睦南道招","box":[[1859,2911],[1959,2918],[1957,2944],[1857,2936]]},{"text":"铁陪同","box":[[1631,2925],[1693,2928],[1692,2951],[1629,2947]]},{"text":"操坏蛋。那些犯错误的干部也没有机会锻炼和改造自","box":[[1991,2918],[2597,2954],[2595,2984],[1989,2948]]},{"text":"7月4日、","box":[[1154,2939],[1239,2947],[1236,2974],[1152,2966]]},{"text":"待所","box":[[1859,2935],[1906,2935],[1906,2958],[1859,2958]]},{"text":"1963年","box":[[1098,2945],[1160,2945],[1160,2967],[1098,2967]]},{"text":"参观塘沽永利化工厂（现东风化工厂），并","box":[[369,2955],[729,2960],[729,2985],[369,2981]]},{"text":"借工作之名，行游玩之实来津","box":[[1254,2946],[1501,2959],[1500,2986],[1253,2973]]},{"text":"5月初","box":[[294,2957],[353,2957],[353,2979],[294,2979]]},{"text":"己，这是刘少奇一箭三雕的卑部使俩！刘少奇还大肆","box":[[1996,2948],[2598,2986],[2596,3018],[1994,2980]]},{"text":"货敬等陪同","box":[[742,2967],[841,2972],[839,2999],[741,2994]]},{"text":"5日","box":[[1169,2964],[1213,2968],[1211,2990],[1167,2986]]},{"text":"王光美同来","box":[[1630,2962],[1729,2966],[1728,2993],[1629,2990]]},{"text":"住原河北省","box":[[1857,2962],[1956,2968],[1954,2993],[1856,2988]]},{"text":"与资本家进行座谈","box":[[371,2976],[524,2979],[523,3001],[370,2997]]},{"text":"遵义道招待","box":[[1857,2983],[1956,2989],[1954,3014],[1856,3009]]},{"text":"宣楊“在我們专政的条件下搞苹命总是好苹”，这是地","box":[[1996,2982],[2598,3019],[2596,3051],[1994,3013]]},{"text":"9月28日","box":[[1170,3006],[1260,3006],[1260,3032],[1170,3032]]},{"text":"访问朝鲜回国经天津车站，停四十分钟","box":[[1248,3009],[1574,3022],[1573,3048],[1247,3035]]},{"text":"所","box":[[1859,3005],[1882,3005],[1882,3023],[1859,3023]]},{"text":"月","box":[[324,3020],[351,3020],[351,3038],[324,3038]]},{"text":"召开工商业家座谈会，并作了讲话","box":[[371,3015],[653,3017],[653,3043],[371,3041]]},{"text":"王光英、宋装购、周叔张、","box":[[743,3018],[949,3026],[948,3054],[742,3045]]},{"text":"地道道的阶级斗争熄灭谕，麻痹苹命人民斗志的烟策","box":[[1992,3013],[2598,3051],[2596,3081],[1991,3044]]},{"text":"5","box":[[297,3025],[308,3025],[308,3035],[297,3035]]},{"text":"林铁、刘子厚前往迎接","box":[[1629,3023],[1821,3031],[1819,3058],[1628,3050]]},{"text":"李烛尘等参加","box":[[744,3039],[862,3045],[861,3070],[742,3065]]},{"text":"1964年","box":[[1096,3045],[1159,3049],[1157,3072],[1095,3068]]},{"text":"6月29日","box":[[1164,3049],[1260,3049],[1260,3074],[1164,3074]]},{"text":"来津，听省、市委汇报","box":[[1248,3050],[1444,3058],[1443,3084],[1247,3076]]},{"text":"弹。毛主席教导我們说：“帝国主义者和国内反动派决","box":[[1994,3044],[2597,3084],[2594,3116],[1992,3075]]},{"text":"由刘子厚、间达开、李额","box":[[1629,3063],[1842,3075],[1840,3100],[1628,3089]]},{"text":"5","box":[[291,3080],[308,3080],[308,3096],[291,3096]]},{"text":"月","box":[[329,3079],[350,3079],[350,3097],[329,3097]]},{"text":"参观天津自行车厂","box":[[369,3078],[519,3074],[519,3100],[370,3103]]},{"text":"王光英等陪同","box":[[742,3079],[857,3084],[856,3111],[741,3106]]},{"text":"住原河北省","box":[[1857,3076],[1954,3081],[1953,3105],[1856,3100]]},{"text":"不甘心于他們的失败，他們还要作最后的扎。在全","box":[[1990,3075],[2598,3114],[2596,3149],[1987,3110]]},{"text":"伯、张承先、万晓塘、赵","box":[[1632,3088],[1838,3097],[1838,3119],[1631,3109]]},{"text":"武成、王六之、白桦等参","box":[[1629,3103],[1840,3114],[1839,3140],[1628,3128]]},{"text":"遵义道招待","box":[[1859,3097],[1954,3102],[1953,3125],[1857,3119]]},{"text":"召开市、局长以上千部会（在原南开中学）","box":[[369,3117],[716,3118],[716,3144],[369,3142]]},{"text":"国平定以后，他們也还会以各种方式从事破坏和乱，","box":[[1993,3109],[2594,3149],[2592,3179],[1991,3139]]},{"text":"5","box":[[290,3120],[312,3120],[312,3139],[290,3139]]},{"text":"月","box":[[329,3120],[351,3120],[351,3141],[329,3141]]},{"text":"加并汇报","box":[[1630,3125],[1709,3129],[1708,3152],[1629,3148]]},{"text":"所","box":[[1861,3120],[1877,3120],[1877,3135],[1861,3135]]},{"text":"7月1日","box":[[1170,3147],[1260,3147],[1260,3173],[1170,3173]]},{"text":"听取天津驻军负资同志汇报，并讲话","box":[[1249,3148],[1552,3159],[1551,3185],[1248,3174]]},{"text":"他們将每日每时企图在中国复辟。这是必然的，毫无","box":[[1993,3140],[2595,3182],[2593,3212],[1991,3170]]},{"text":"1951年","box":[[215,3162],[272,3162],[272,3185],[215,3185]]},{"text":"11'","box":[[290,3163],[323,3163],[323,3182],[290,3182]]},{"text":"月","box":[[315,3162],[351,3162],[351,3185],[315,3185]]},{"text":"小、","box":[[374,3165],[411,3165],[411,3183],[374,3183]]},{"text":"参观华北物资交流会","box":[[404,3162],[576,3162],[576,3183],[404,3183]]},{"text":"王光美同来，由黄敬、王","box":[[742,3159],[955,3167],[954,3199],[741,3190]]},{"text":"住云南路招","box":[[969,3168],[1066,3173],[1064,3200],[967,3195]]},{"text":"部队军级以上及省委常委","box":[[1631,3161],[1836,3175],[1834,3200],[1629,3187]]},{"text":"二、与王光英促腺谈心","box":[[368,3180],[560,3179],[560,3204],[368,3206]]},{"text":"疑义的，我们务必不要松懈自己的警惕性。”刘少寺","box":[[1991,3172],[2595,3214],[2593,3244],[1989,3202]]},{"text":"光英等陪同","box":[[744,3186],[840,3186],[840,3207],[744,3207]]},{"text":"待所","box":[[972,3189],[1014,3195],[1011,3217],[968,3211]]},{"text":"乡加","box":[[1630,3186],[1672,3186],[1672,3209],[1630,3209]]},{"text":"7月2日","box":[[1172,3209],[1260,3209],[1260,3234],[1172,3234]]},{"text":"召开河北省各地委书记座谈会","box":[[1248,3208],[1496,3218],[1495,3244],[1247,3234]]},{"text":"却公然和毛席的教导唱反调，其目的要在我国实现","box":[[1991,3204],[2597,3247],[2594,3277],[1989,3234]]},{"text":"1953年","box":[[213,3222],[272,3222],[272,3245],[213,3245]]},{"text":"一","box":[[372,3225],[411,3225],[411,3244],[372,3244]]},{"text":"刘少奇全家来津","box":[[402,3219],[545,3219],[545,3245],[402,3245]]},{"text":"王光美及其小孩同来，","box":[[742,3231],[917,3236],[916,3262],[741,3257]]},{"text":"住云南路招","box":[[969,3228],[1066,3233],[1064,3261],[967,3255]]},{"text":"各地委书记参加","box":[[1628,3222],[1764,3229],[1762,3256],[1626,3249]]},{"text":"二、与王光英促隙谈心","box":[[369,3241],[558,3239],[558,3265],[369,3266]]},{"text":"“和平演变”，为他复辟资本主义作奥准备。","box":[[1988,3234],[2499,3273],[2497,3303],[1986,3264]]},{"text":"待所","box":[[968,3253],[1010,3253],[1010,3275],[968,3275]]},{"text":"7月3日","box":[[1170,3250],[1251,3250],[1251,3275],[1170,3275]]},{"text":"参加天津市委书记座谈会","box":[[1249,3251],[1459,3257],[1458,3283],[1248,3276]]},{"text":"王光美同来，由刘子厚、","box":[[742,3278],[938,3288],[937,3315],[741,3305]]},{"text":"告诉你刘少奇，妄想让我們丧失警惕吗？一万个","box":[[2042,3270],[2592,3312],[2590,3342],[2040,3300]]},{"text":"1958年","box":[[213,3283],[273,3283],[273,3305],[213,3305]]},{"text":"7月8日视察武清县（杨村）","box":[[273,3280],[530,3278],[530,3305],[273,3307]]},{"text":"住险南道招","box":[[968,3292],[1066,3295],[1065,3321],[968,3317]]},{"text":"7月5日","box":[[1169,3293],[1248,3293],[1248,3314],[1169,3314]]},{"text":"参加河北省委书记座谈会","box":[[1251,3290],[1460,3298],[1459,3324],[1250,3316]]},{"text":"省公安厅张明河等陪同","box":[[742,3300],[934,3310],[932,3336],[741,3326]]},{"text":"办不到，毛主席早在八届十中全会上提出“千万不要","box":[[1990,3297],[2595,3343],[2593,3377],[1987,3332]]},{"text":"待所","box":[[969,3311],[1011,3315],[1008,3338],[967,3333]]},{"text":"晚","box":[[1167,3316],[1185,3316],[1185,3330],[1167,3330]]},{"text":"忘記阶级斗事”的伟大号召，苹命人民一定要牢记这","box":[[1989,3329],[2594,3376],[2591,3411],[1986,3364]]},{"text":"7月9日","box":[[285,3343],[357,3343],[357,3366],[285,3366]]},{"text":"听取省市负责人汇报","box":[[401,3340],[579,3339],[579,3364],[401,3366]]},{"text":"由阅达开、吴砚农、解学","box":[[742,3340],[949,3350],[947,3377],[741,3367]]},{"text":"二","box":[[370,3350],[405,3346],[407,3364],[372,3368]]},{"text":"7月5日4","box":[[1164,3349],[1261,3353],[1260,3378],[1163,3375]]},{"text":"会上由王光美作“桃圆经验”的报告（在第","box":[[1246,3349],[1612,3362],[1611,3392],[1245,3379]]},{"text":"参观天津市工业大跃进展览会","box":[[398,3360],[653,3358],[653,3384],[398,3386]]},{"text":"恭、张承先等汇报","box":[[740,3361],[896,3368],[895,3393],[739,3387]]},{"text":"下午，","box":[[1164,3373],[1217,3373],[1217,3395],[1164,3395]]},{"text":"刘子摩掌握会议，天津市","box":[[1623,3365],[1837,3377],[1836,3404],[1622,3393]]},{"text":"一点，决不会上你的当。","box":[[1997,3365],[2260,3383],[2258,3413],[1995,3395]]},{"text":"一工人文化宫）","box":[[1255,3379],[1375,3383],[1374,3410],[1254,3406]]},{"text":"7月10日","box":[[285,3399],[357,3399],[357,3426],[285,3426]]},{"text":"召开天津市街道干部和居民代表座谈会","box":[[405,3399],[725,3401],[725,3428],[405,3426]]},{"text":"6日上午","box":[[1168,3390],[1238,3393],[1237,3416],[1167,3412]]},{"text":"吴砚农、万晓塘、谷云亭、","box":[[742,3400],[946,3410],[945,3436],[741,3426]]},{"text":"十七级以上干部多加","box":[[1626,3396],[1800,3404],[1798,3430],[1625,3421]]},{"text":"（在天津市俱乐部）","box":[[414,3422],[567,3420],[567,3441],[414,3443]]},{"text":"李权超等陪同、王光美作题","box":[[742,3420],[956,3431],[955,3457],[741,3445]]},{"text":"7月6日","box":[[1169,3431],[1242,3431],[1242,3453],[1169,3453]]},{"text":"与河北省委负贵人谈话","box":[[1249,3432],[1442,3437],[1442,3463],[1248,3458]]},{"text":"刘少奇的这篇黑讲话，只不过是他难以数计的黑","box":[[2040,3428],[2589,3475],[2587,3507],[2037,3460]]},{"text":"召开市文教干部座谈会（即半工半读座","box":[[407,3441],[725,3441],[725,3462],[407,3462]]},{"text":"译张承先、刘子厚、万晓塘、","box":[[741,3439],[955,3451],[953,3476],[739,3465]]},{"text":"谈会，在天津市俱乐部）","box":[[405,3460],[604,3456],[605,3482],[405,3485]]},{"text":"王元之等陪同，娄平参加","box":[[743,3462],[947,3472],[946,3493],[742,3483]]},{"text":"下午","box":[[1170,3453],[1206,3453],[1206,3472],[1170,3472]]},{"text":"话中的一部分。铁证如山！刘少奇，你反毛泽东思想罪","box":[[1990,3459],[2589,3505],[2587,3537],[1987,3491]]},{"text":"10月","box":[[1172,3490],[1235,3490],[1235,3517],[1172,3517]]},{"text":"王光美以刘少奇代表身份来天津听取词北省","box":[[1251,3489],[1606,3504],[1605,3531],[1250,3517]]},{"text":"召开几个工厂的工人座谈会","box":[[371,3499],[594,3499],[594,3524],[371,3524]]},{"text":"责难逃！让我们无产阶级革命造反派高举起革命批判","box":[[1990,3490],[2589,3539],[2587,3571],[1987,3522]]},{"text":"7月","box":[[294,3502],[350,3502],[350,3523],[294,3523]]},{"text":"委的汇报","box":[[1251,3513],[1330,3517],[1329,3538],[1250,3535]]},{"text":"大旗，彻底清算刘少奇反毛泽东思想的天罪行，彻","box":[[1987,3519],[2589,3569],[2586,3604],[1984,3554]]},{"text":"7月11日","box":[[287,3541],[357,3541],[357,3564],[287,3564]]},{"text":"视察鸿顺里","box":[[368,3539],[467,3539],[467,3565],[368,3565]]},{"text":"刘子厚、万晓塘、樊青典、","box":[[742,3542],[946,3549],[945,3574],[741,3568]]},{"text":"王光美投桃园大地主赵学輸的女儿，天津大","box":[[1249,3550],[1606,3562],[1605,3590],[1248,3577]]},{"text":"底砸烂刘少奇的形“左”实右的反动路线。","box":[[1988,3552],[2504,3595],[2501,3626],[1986,3584]]},{"text":"吴砚农、王光美等陪同","box":[[740,3563],[932,3570],[931,3596],[739,3589]]},{"text":"学的反动学生赵xx谈质","box":[[1250,3571],[1460,3577],[1460,3603],[1250,3597]]},{"text":"打创中国党内头号走资本主义道路的当权派刘少","box":[[2038,3588],[2585,3634],[2582,3666],[2035,3620]]},{"text":"奇！","box":[[2066,3630],[2104,3630],[2104,3654],[2066,3654]]}],"dimensions":{"height":3769,"width":2785}}