{"ocr_results":[{"text":"红色风暴","box":[[291,204],[522,204],[522,286],[291,286]]},{"text":"敬祝毛主席万寿无罐","box":[[1179,240],[1664,243],[1663,291],[1178,287]]},{"text":"1968年9月27日星期五第2版","box":[[1989,243],[2581,253],[2580,309],[1988,299]]},{"text":"安吉捉到胡宗南狗弟胡宗萍","box":[[419,370],[2429,370],[2429,523],[419,523]]},{"text":"本报记者","box":[[1300,548],[1536,548],[1536,590],[1300,590]]},{"text":"浙北大地红旗招揭，天自山下战整齐唱。","box":[[319,622],[847,636],[845,676],[318,661]]},{"text":"而不敢声张。这一点，潘敦父的小老婆也还记忆犹新，时响波及全县。","box":[[1042,639],[1996,637],[1996,685],[1042,686]]},{"text":"在省革零会的直接领导下，安吉县的无产阶级革命派，至今日，她不敢抵赖地说：当时，我一听到脚步声，就","box":[[316,662],[1799,679],[1798,729],[315,712]]},{"text":"与此同时，胡宗萍一面制造舆论，抗拒中央指示，叫","box":[[1881,662],[2587,670],[2587,726],[1880,718]]},{"text":"和广大革命群众充分地发动起来了。他们组织起干干万万","box":[[261,701],[1018,718],[1017,755],[261,738]]},{"text":"噢什么：“中央指示，不适合地方”，还拼命地鼓欢什么：","box":[[1822,703],[2572,709],[2572,762],[1821,756]]},{"text":"知道是阿楼来了”。","box":[[1041,719],[1295,724],[1295,755],[1040,750]]},{"text":"的民众、调动丁浩浩满荡的革命大军，向国民党反动派的大","box":[[261,739],[1015,756],[1014,791],[261,774]]},{"text":"“所有的当权派都应该统统批斗、打倒”，一面则处心积","box":[[1810,738],[2589,746],[2588,803],[1809,795]]},{"text":"由此可见，胡宗萍这个反动家伙，与毛万里、胡维","box":[[1104,756],[1797,761],[1797,796],[1104,791]]},{"text":"军间、大战卫胡察南的老巢杀过去了，杀得一小操阶级敌","box":[[260,776],[1018,793],[1017,829],[259,812]]},{"text":"勾，虑地网罗、拉拢和培植自己的反动势力，密谋指了一批","box":[[1778,777],[2589,785],[2588,841],[1777,833]]},{"text":"藩，潘敦父等反动头目的关系，以及他所干的一切罪恶勾","box":[[1045,792],[1797,797],[1797,834],[1045,829]]},{"text":"人，资端落鸽，胆战心惊。真是锋芒指处，所向披魔。现","box":[[261,815],[1016,831],[1016,866],[261,850]]},{"text":"国民党的残渣余擎、五类分子的子女、没有得到改造的资","box":[[1819,817],[2587,823],[2587,876],[1818,870]]},{"text":"当，也非常人可比！","box":[[1050,832],[1297,835],[1296,866],[1049,862]]},{"text":"在，初成一举，已经挖出了暗藏的叛徒、特务、土等反","box":[[261,853],[1013,867],[1013,904],[261,890]]},{"text":"产阶级臭知识分子，以及一些来路不明、有严重改治所史","box":[[1779,856],[2587,863],[2587,914],[1779,908]]},{"text":"一九四九年四月在蒋介石王朝面临全面崩溃的前","box":[[1100,867],[1797,873],[1797,910],[1099,904]]},{"text":"草命分手三百十二名，其中有长期被认为已逃亡台湾的国","box":[[260,890],[1015,904],[1014,940],[259,926]]},{"text":"问题的人，充当了某些群众组织的头头、军师和打手。这","box":[[1778,891],[2589,899],[2588,956],[1777,948]]},{"text":"夕，胡宗南还亲自派了飞机，命令军统特务蒋炳筋到杭州","box":[[1045,905],[1797,911],[1797,948],[1045,942]]},{"text":"民党中将一名，少将两名。并且活捉了胡宗南的狗弟、暗","box":[[260,928],[1013,943],[1012,980],[259,964]]},{"text":"些人，在文教系统中，或在生产大队里都有。例如，宁","box":[[1820,931],[2587,939],[2587,990],[1820,983]]},{"text":"来接他，要他同胡宗南在孝丰老巢的家属一起飞逃台湾。","box":[[1045,945],[1783,951],[1783,983],[1045,977]]},{"text":"藏的军统特务、阴谋破坏无产阶级文化大革命的反革命分","box":[[258,966],[1013,980],[1013,1016],[258,1002]]},{"text":"当时，胡宗萍与蒋炳舫曾为此事就商于毛万里。毛万里则","box":[[1042,980],[1797,986],[1797,1022],[1042,1016]]},{"text":"波市巡官警察长的儿子，赤坞中心小学的袁义，伪孝丰","box":[[1819,973],[2587,980],[2587,1027],[1818,1021]]},{"text":"于一胡宗萍。","box":[[259,999],[466,1009],[464,1046],[257,1035]]},{"text":"立即派出车子，将胡宗南的家属全部接上飞机，而专门布","box":[[1045,1016],[1796,1025],[1795,1062],[1045,1053]]},{"text":"县保安自卫队长的儿子、小学教员叶X；恶霸地主的儿","box":[[1820,1011],[2587,1018],[2587,1065],[1820,1059]]},{"text":"置让胡宗萍“留下”。","box":[[1047,1056],[1330,1062],[1329,1094],[1046,1087]]},{"text":"子、腐化落分子贾×X；为反革命分子翻案的、伪宪兵","box":[[1822,1051],[2589,1057],[2588,1103],[1821,1097]]},{"text":"一、胡宗萍究竟是什么货色？","box":[[352,1065],[843,1071],[843,1108],[352,1101]]},{"text":"一九四九年五月四日，杭州解放以后，胡宗萍即改名","box":[[1098,1094],[1797,1100],[1797,1135],[1098,1129]]},{"text":"的儿子马××；叛徒的儿子、本人奸污过九个女人的犯罪","box":[[1812,1089],[2587,1094],[2587,1141],[1812,1136]]},{"text":"胡宗萍究竟是什么货色，他是怎样潜伏下来的：现据","box":[[320,1119],[1019,1132],[1019,1169],[320,1156]]},{"text":"换姓，拿着一张署名“方中天”的高中毕业证书（据说这","box":[[1039,1130],[1796,1138],[1795,1175],[1039,1167]]},{"text":"分子任×X；来路不明、历史不清、受过清洗的投机倒把","box":[[1782,1130],[2587,1135],[2587,1178],[1782,1173]]},{"text":"揭发调查，已经真相大白。","box":[[260,1157],[621,1167],[620,1199],[259,1189]]},{"text":"个叫方中天的本人，在解放前夕“自杀”），于六月十九","box":[[1045,1168],[1797,1178],[1797,1213],[1045,1203]]},{"text":"分子，贪污分子林××、李××，以及混进党内，人们称","box":[[1815,1168],[2587,1174],[2587,1216],[1815,1209]]},{"text":"胡宗萍就是胡宗南的嫡亲狗堂弟，是一个货真价实的","box":[[320,1196],[1019,1205],[1019,1241],[320,1232]]},{"text":"日考进浙江干校，并在经过三个月的学习以后，由浙江干","box":[[1007,1206],[1794,1216],[1794,1251],[1007,1241]]},{"text":"之为“抹桌布”的蜕化变质分子翁××，等等，等等，举","box":[[1820,1205],[2589,1213],[2588,1254],[1820,1246]]},{"text":"国民党军统大特务。他原名胡琴楼，小名叫阿楼，老巢安","box":[[258,1232],[1021,1246],[1020,1281],[258,1267]]},{"text":"校政治部的×××介绍入团，派给工作。","box":[[1035,1244],[1565,1254],[1565,1286],[1034,1276]]},{"text":"不胜举。就是这些人，和胡宗萍站在同一条阵线上，打着","box":[[1823,1247],[2586,1254],[2585,1290],[1823,1284]]},{"text":"吉县孝丰城北鹤溪。狗父胡俊卿，是伪孝丰县长王贵清的","box":[[260,1272],[1013,1286],[1013,1318],[259,1304]]},{"text":"从此，胡宗萍这个极端反动的军统特务分子，就这样","box":[[1103,1282],[1797,1289],[1797,1325],[1102,1319]]},{"text":"“红旗”反红旗，把自己打扮成为所谓“响当当的老造反","box":[[1790,1284],[2586,1292],[2585,1328],[1789,1320]]},{"text":"同；狗兄胡宗棠，是胡宗南部下营长，二堂兄胡宗","box":[[260,1310],[1018,1322],[1017,1354],[259,1342]]},{"text":"潜伏下来，混进我们的队伍，并在一九五六年以后，一直","box":[[1041,1320],[1835,1328],[1835,1363],[1040,1355]]},{"text":"派”。他们中间的某些人，在过去和现在都扮演着十分可","box":[[1815,1322],[2584,1330],[2584,1366],[1815,1358]]},{"text":"宾，是国民党军统特务武装组织“忠义救国军”上校参谋。","box":[[260,1348],[1001,1359],[1001,1391],[259,1380]]},{"text":"避居于浙北边境、天目山下的白水湾，担任“小学教师”。耻的角色，甚至充当了胡宗萍的爪牙和卫士；他们对胡宗","box":[[1044,1355],[2586,1366],[2585,1407],[1043,1396]]},{"text":"胡宗萍从小依仗胡宗南养和培植，很早就拜倒在军","box":[[320,1386],[1013,1398],[1013,1430],[320,1418]]},{"text":"毛主席教导我们：“反草命分子怎样要两面派手法呢？","box":[[1103,1396],[1790,1406],[1789,1441],[1102,1431]]},{"text":"萍言听计从，俯首听命。","box":[[1817,1402],[2147,1406],[2147,1438],[1817,1434]]},{"text":"统特务头子戴笠门下，曾亲受戴笠“赐予”的“大红包”，","box":[[260,1421],[1003,1433],[1002,1468],[259,1456]]},{"text":"他們怎样以假象欺我們，而在暗里却干着我們意料不到","box":[[1045,1433],[1794,1442],[1794,1477],[1045,1468]]},{"text":"胡宗萍说：“还是搞武斗好”。他们就上山下地，挨","box":[[1879,1439],[2587,1445],[2587,1482],[1879,1476]]},{"text":"一九四二年，先后加入了伪三青团、国民党、“忠义救国","box":[[260,1457],[1018,1473],[1017,1508],[259,1492]]},{"text":"的事情呢？这一切，成千成万的善食人是不知道的。就是","box":[[1042,1471],[1794,1479],[1794,1515],[1042,1507]]},{"text":"家挨户的动员一部分不明真相的贫下中农，对持有不同观","box":[[1815,1475],[2586,1483],[2585,1520],[1815,1512]]},{"text":"军”，一九四三年，曾在安微广德“忠义救国军总指挥","box":[[258,1495],[1015,1509],[1014,1544],[258,1530]]},{"text":"因为这个故，許多反革命分子钻进我們的队伍中来了。","box":[[1042,1507],[1788,1517],[1788,1553],[1042,1544]]},{"text":"点的群众组织和另一部分贫下中农，进行抄家、武斗，甚","box":[[1822,1515],[2586,1523],[2585,1558],[1821,1550]]},{"text":"部”担任副官，亲受“忠义救国军总指挥”马志超（胡宗","box":[[260,1536],[1012,1549],[1011,1581],[259,1568]]},{"text":"胡宗萍就是这样一个钻进我们队伍中来的反革命分","box":[[1107,1548],[1790,1556],[1789,1588],[1107,1580]]},{"text":"至企图谋杀贫下中农群众。","box":[[1820,1556],[2178,1559],[2177,1590],[1820,1587]]},{"text":"南部下师长）的特别训练，并与“忠义救国军”上校参谋","box":[[260,1574],[1013,1585],[1013,1617],[259,1606]]},{"text":"子","box":[[1051,1593],[1074,1593],[1074,1611],[1051,1611]]},{"text":"胡宗萍阴谋制造分裂，破坏革命大联合，叫嚣什么：","box":[[1881,1591],[2568,1597],[2567,1634],[1880,1628]]},{"text":"胡宗宾一起，积极反共，残酷镇压安徽屯溪柏山中学的学","box":[[258,1611],[1012,1625],[1011,1655],[258,1641]]},{"text":"“大联合是和稀泥、是右倾”，“坚决不能联合”。他们","box":[[1835,1628],[2584,1637],[2584,1674],[1835,1664]]},{"text":"生运动。","box":[[255,1647],[370,1651],[369,1683],[254,1679]]},{"text":"二、胡宗萍在文化大革命中的破坏活动","box":[[1129,1641],[1788,1649],[1788,1686],[1128,1678]]},{"text":"即撕毁协议，另树旗帜，重拉山头，竭力破坏革命大联合。","box":[[1822,1666],[2571,1677],[2570,1713],[1821,1702]]},{"text":"一九四六年，胡宗南“衣锦还乡”时，胡宗萍又亲受","box":[[317,1687],[1013,1699],[1013,1730],[317,1717]]},{"text":"胡宗萍潜伏下来的目的，为了什么呢？","box":[[1107,1699],[1591,1707],[1590,1739],[1107,1731]]},{"text":"胡宗萍恶毒地攻击中国人民解放军，蓄意毁我长城，","box":[[1884,1708],[2566,1718],[2566,1750],[1883,1740]]},{"text":"胡宗南的“面试”，并于同年二月，由胡宗南亲自带领他","box":[[257,1723],[1012,1736],[1011,1768],[256,1755]]},{"text":"很简单，就是为了破坏我们的无产阶级革命和无产阶","box":[[1103,1739],[1790,1748],[1789,1778],[1102,1769]]},{"text":"大骂“解放军支左有问题”。他们即拼命的攻击和殴打","box":[[1817,1746],[2583,1756],[2582,1788],[1817,1778]]},{"text":"到杭州×X路三号，会见了军统特务浙江组长毛万里；到","box":[[257,1761],[1019,1775],[1019,1806],[256,1792]]},{"text":"级专政，颠覆无产阶级政权，实行反革命复辟。因此，在","box":[[1003,1775],[1790,1786],[1789,1816],[1002,1806]]},{"text":"支左的解放军同志，叫什么：“解放军我们就是信不","box":[[1811,1780],[2584,1794],[2584,1829],[1810,1815]]},{"text":"XX巷五十八号，会见了伪浙江三青团干事长，中统浙江","box":[[260,1798],[1019,1812],[1019,1844],[259,1830]]},{"text":"这次史无前例的无产阶级文化大革命中，他从阴暗角落里","box":[[1038,1810],[1788,1821],[1788,1856],[1037,1845]]},{"text":"过”。甚至诬骂我们解放军是“国民党军队”，是“刘邓","box":[[1817,1821],[2583,1835],[2582,1867],[1817,1853]]},{"text":"方面的头目胡维藩；到××街××巷五号，会见了伪浙江","box":[[258,1837],[1019,1852],[1019,1882],[258,1868]]},{"text":"跳了出来，这是必然的毫无疑义的。","box":[[1036,1850],[1508,1856],[1507,1888],[1036,1882]]},{"text":"兵”，“非赶走不可”，等等。","box":[[1817,1854],[2242,1859],[2241,1902],[1817,1897]]},{"text":"省参议院少将参议员潘敦父等头面反动人物。在胡宗南临","box":[[258,1876],[1012,1888],[1011,1918],[258,1906]]},{"text":"在文化大革命初期，胡宗萍首先给人以假象，而将其","box":[[1101,1886],[1787,1896],[1786,1931],[1101,1921]]},{"text":"胡宗萍说：“赤坞要大乱，安吉要大乱。”他们即到处","box":[[1879,1897],[2583,1909],[2582,1944],[1879,1932]]},{"text":"走时，曾特别瞩咐毛万里等人，对胡宗萍“要多加关","box":[[257,1912],[1012,1925],[1011,1956],[256,1944]]},{"text":"真象荫蔽起来，千方百计地把自己装扮得比革命还要“革","box":[[1038,1924],[1788,1935],[1788,1967],[1037,1956]]},{"text":"串连，准备土枪土炮，甚至一直窜到安微边境一带搞武器。","box":[[1816,1935],[2565,1949],[2564,1984],[1815,1970]]},{"text":"照”，而对胡宗萍则说：“以后有什么事情，尽管我你毛","box":[[254,1950],[1013,1963],[1013,1995],[253,1982]]},{"text":"命”的样子。他戴着“革命”的面具，曾经自吹自擂，标","box":[[1035,1959],[1791,1972],[1791,2008],[1034,1996]]},{"text":"胡宗萍说：“联合！联合！联合起来就是为了要揪我老","box":[[1876,1974],[2583,1985],[2582,2022],[1876,2011]]},{"text":"大哥好了”。","box":[[252,1988],[426,1993],[425,2025],[251,2020]]},{"text":"榜自己是什么：“贫农出身的转业军人”，“革命的人民","box":[[1039,1997],[1790,2008],[1789,2045],[1039,2034]]},{"text":"胡。”他们即想方设法，到处发声明，提抗议，公布“调","box":[[1817,2011],[2583,2025],[2582,2061],[1817,2047]]},{"text":"在解放以前，胡宗萍是一个“红”得发紫的人物。靠","box":[[316,2026],[1013,2037],[1013,2069],[315,2058]]},{"text":"A","box":[[1796,2023],[1815,2023],[1815,2035],[1796,2035]]},{"text":"教师”、“资产阶级反动路线的受害者”，等等。骗取群","box":[[1033,2035],[1790,2046],[1789,2083],[1033,2072]]},{"text":"查报告”，甚至公开召集群众大会，为胡宗萍歌功颂德。","box":[[1810,2050],[2571,2065],[2570,2100],[1809,2085]]},{"text":"山硬，吃得开，手中又有毛万里，胡维藩、潘敦父等人的","box":[[254,2064],[1013,2077],[1013,2107],[253,2095]]},{"text":"众的同情、支持和信任。","box":[[1003,2075],[1353,2080],[1352,2112],[1002,2107]]},{"text":"在两年多的无产阶级文化大革命中，安吉孝丰城西赤","box":[[1879,2088],[2583,2101],[2582,2139],[1879,2126]]},{"text":"许多“名片”，不仅可以在杭州安定中学、宗文中学、杭","box":[[255,2101],[1012,2115],[1011,2147],[255,2133]]},{"text":"接着，胡宗萍就打着“造反”的旗号，从天目山下的","box":[[1094,2111],[1790,2121],[1789,2157],[1093,2148]]},{"text":"坞公社，为什么一度出现了许许多多值得令人深思的事情：","box":[[1817,2125],[2578,2142],[2577,2179],[1816,2161]]},{"text":"高、浙大等学校，自由进出，大搞特务活动，而且在国民","box":[[254,2139],[1010,2154],[1010,2185],[253,2169]]},{"text":"一个从不闻名的小小的白水湾“杀”出来，“杀”到白杨","box":[[1032,2149],[1788,2162],[1788,2197],[1031,2184]]},{"text":"无产阶级司令部的声音传不进，国民党的残渣余却","box":[[1876,2163],[2584,2179],[2583,2220],[1876,2204]]},{"text":"党的官场上，也是横撞直闯，通行无阻，可以说他要什么有","box":[[254,2175],[1015,2189],[1014,2224],[253,2210]]},{"text":"大队和白杨小学；“杀”到赤坞公社的各个大队和赤坞公","box":[[1030,2190],[1785,2201],[1785,2232],[1030,2221]]},{"text":"在那里发号施令；","box":[[1819,2199],[2048,2211],[2046,2243],[1818,2231]]},{"text":"什么，谁都不敢得罪他，就是连特务头子毛万里的小老","box":[[255,2213],[1012,2229],[1011,2261],[255,2245]]},{"text":"社中心小学，甚至一直“杀”到孝丰镇，以及邻近的几个","box":[[1035,2225],[1785,2238],[1785,2273],[1034,2260]]},{"text":"地、富、反、坏，逍遥法外；牛鬼蛇神，神气活现，","box":[[1876,2241],[2562,2256],[2561,2293],[1876,2277]]},{"text":"婆，或者潘敦父的小老婆，都得让他三分，“听其摆布”","box":[[254,2251],[1019,2268],[1019,2299],[253,2282]]},{"text":"公社，乃至安吉县整个文教系统。顿然之间，胡宗萍的影","box":[[1033,2265],[1790,2276],[1789,2311],[1033,2300]]},{"text":"（下轉第三版）","box":[[2254,2291],[2461,2294],[2461,2329],[2253,2326]]},{"text":"Aearaeeceaeeae","box":[[566,2307],[812,2316],[811,2337],[565,2329]]},{"text":"1161618184646161","box":[[1436,2326],[1644,2329],[1644,2344],[1436,2341]]},{"text":"舟山百货公司广大无产","box":[[313,2350],[613,2357],[612,2392],[312,2385]]},{"text":"阶级革命派，在省革委会的","box":[[251,2388],[611,2396],[611,2428],[250,2420]]},{"text":"群众专政威力大","box":[[736,2402],[1360,2405],[1360,2483],[735,2479]]},{"text":"找不到。","box":[[2217,2393],[2323,2393],[2323,2426],[2217,2426]]},{"text":"三十八天破悬案","box":[[1453,2404],[2086,2424],[2083,2506],[1450,2486]]},{"text":"亲切关怀下和省公安厅军管","box":[[252,2426],[611,2434],[611,2466],[252,2458]]},{"text":"又一次，群众采取乘其","box":[[2278,2429],[2581,2434],[2581,2471],[2278,2466]]},{"text":"会、地区公安机关军管会的","box":[[254,2463],[611,2472],[611,2504],[253,2495]]},{"text":"不备的时候，把她叫出来，","box":[[2218,2467],[2562,2474],[2561,2510],[2217,2504]]},{"text":"领导下，认真贯彻伟大领袖","box":[[252,2502],[613,2509],[612,2541],[252,2534]]},{"text":"在广大革命群众面前写","box":[[2216,2504],[2580,2510],[2579,2551],[2215,2545]]},{"text":"舟山百货公司革命造反到底兵团","box":[[1101,2523],[1728,2535],[1727,2576],[1101,2565]]},{"text":"毛主席关于“我們在肃反工","box":[[252,2540],[610,2547],[609,2579],[252,2572]]},{"text":"“战无不胜的毛泽东思想万","box":[[2227,2543],[2577,2551],[2576,2588],[2226,2580]]},{"text":"作中的路是群众肃反的路","box":[[251,2578],[611,2586],[611,2618],[250,2610]]},{"text":"岁！”“打倒刘、邓、陶！”","box":[[2217,2583],[2563,2588],[2563,2624],[2217,2619]]},{"text":"”的教导，充分发动群众，依靠群众专","box":[[251,2616],[790,2627],[790,2659],[250,2648]]},{"text":"下，一场由省、地公安机关军管会解放军","box":[[1437,2630],[1979,2643],[1978,2679],[1436,2666]]},{"text":"“横扫一切牛鬼蛇神”等标","box":[[2228,2621],[2580,2626],[2579,2662],[2228,2657]]},{"text":"按旧规破案不了了之","box":[[921,2638],[1298,2643],[1298,2681],[920,2676]]},{"text":"政的强大成力，仅仅用三十八天时间就","box":[[251,2654],[790,2667],[790,2699],[250,2686]]},{"text":"语，她就立即脸变颜色手发抖，心虚地","box":[[2025,2648],[2580,2664],[2579,2705],[2024,2689]]},{"text":"同志、专业人员、公司无产阶级革命派三","box":[[1432,2666],[1976,2681],[1975,2717],[1431,2703]]},{"text":"破获了一件一年半未破的现行反革命悬","box":[[249,2689],[789,2704],[788,2739],[248,2724]]},{"text":"案件发生数天后，旧公安处才派人","box":[[901,2695],[1385,2702],[1384,2737],[901,2730]]},{"text":"讲：“你们为什么要这样多的人看我","box":[[2027,2686],[2580,2702],[2579,2745],[2026,2729]]},{"text":"结合的“人民战争”打响了。广大无产阶","box":[[1434,2706],[1976,2720],[1975,2755],[1433,2741]]},{"text":"写？并且在写的过程中，明明她平时写","box":[[2024,2721],[2578,2739],[2577,2784],[2023,2767]]},{"text":"案。","box":[[252,2731],[296,2731],[296,2763],[252,2763]]},{"text":"来破案，所来专业人员按照老框框，旧","box":[[842,2737],[1383,2741],[1383,2773],[842,2769]]},{"text":"级革命派，一边认真学习伟大领袖毛主席","box":[[1434,2742],[1976,2758],[1975,2795],[1433,2779]]},{"text":"的“东”字是简化的，这时就写繁体字，","box":[[2021,2759],[2565,2777],[2563,2824],[2019,2806]]},{"text":"常规，首先找了旧商业局搞人事工作的同","box":[[842,2772],[1383,2778],[1383,2813],[842,2807]]},{"text":"有关阶级和阶级斗争的教导，反复回忆","box":[[1435,2780],[1975,2796],[1974,2831],[1434,2815]]},{"text":"奇怪的案件","box":[[386,2791],[642,2799],[641,2841],[385,2832]]},{"text":"群众要她写简化字，她就假装说“我不","box":[[2025,2799],[2578,2815],[2577,2862],[2024,2846]]},{"text":"志了解情况，结果无声无息，束之高阁。","box":[[842,2810],[1366,2816],[1366,2851],[842,2845]]},{"text":"当时的情况，走访当时有关接触此案件","box":[[1435,2817],[1975,2834],[1974,2871],[1434,2853]]},{"text":"过了数月，旧公安处又来人破案，进行个","box":[[839,2846],[1382,2852],[1381,2889],[838,2883]]},{"text":"会写”，叫她写“捣”字，她在十六个","box":[[2027,2838],[2577,2853],[2576,2898],[2026,2884]]},{"text":"一九六六年十二月二十一日下午二时","box":[[315,2863],[789,2879],[788,2914],[314,2898]]},{"text":"的同志，提供线索，使此案件日趋明朗","box":[[1432,2858],[1973,2874],[1972,2906],[1431,2890]]},{"text":"别了解，座谈。正象伟大领袖毛主席所批","box":[[839,2884],[1383,2892],[1383,2929],[838,2921]]},{"text":"“捣”字中有十五个都缺一划，与反动标","box":[[2039,2876],[2578,2891],[2577,2936],[2038,2922]]},{"text":"左右，正当舟山剧院广场召开授越抗美大","box":[[254,2902],[789,2916],[788,2948],[253,2934]]},{"text":"化，一连串的问题都集中到报案者身上。","box":[[1432,2893],[1969,2910],[1968,2945],[1431,2928]]},{"text":"语上所写的完全一样。遵照毛主席的“专","box":[[2022,2913],[2575,2929],[2574,2974],[2021,2958]]},{"text":"评的那样：“或者邀集一堆人，不作调查，","box":[[840,2924],[1360,2928],[1360,2963],[840,2959]]},{"text":"会之际，舟山百货分公司旧支部书记刘镇","box":[[252,2940],[789,2954],[788,2985],[251,2971]]},{"text":"为什么她去报案时要讲“会不会是小孩","box":[[1435,2933],[1975,2950],[1974,2982],[1434,2965]]},{"text":"而只是更思苦索地想办法”，打主","box":[[839,2960],[1380,2967],[1380,3003],[838,2997]]},{"text":"政是群众的专政”的教导，终于用毛泽东","box":[[2022,2951],[2574,2967],[2573,3012],[2021,2996]]},{"text":"美急急忙忙地跑进会场，把旧支部委员尹","box":[[254,2977],[790,2991],[790,3023],[253,3009]]},{"text":"放进去的”为什么她要破坏现场：为","box":[[1431,2969],[1973,2987],[1972,3022],[1430,3004]]},{"text":"思想的强大威力，揪出了这个现行反革命","box":[[2022,2987],[2575,3005],[2574,3052],[2021,3034]]},{"text":"意’。”他们对公司广大革命群众则认为与","box":[[839,2998],[1379,3005],[1378,3041],[838,3035]]},{"text":"X×叫到某地，对他说：“在我办公桌上墨","box":[[254,3013],[789,3028],[788,3059],[253,3045]]},{"text":"什么对这样的反革命案件自报案后不理不","box":[[1434,3009],[1972,3026],[1971,3058],[1433,3041]]},{"text":"此案件无关，反而怕泄密。于是就这样找这","box":[[839,3036],[1379,3043],[1378,3079],[838,3073]]},{"text":"分子刘镇美。","box":[[2024,3028],[2193,3038],[2192,3070],[2022,3060]]},{"text":"水瓶底下发现一张反动标语，是我去拿两","box":[[252,3050],[789,3066],[788,3098],[251,3082]]},{"text":"踩，为什么访问她侄女、女儿时所讲情况","box":[[1429,3045],[1972,3061],[1971,3096],[1428,3080]]},{"text":"些人关在办公室里，整天分析研究，研究","box":[[839,3073],[1380,3081],[1380,3117],[838,3109]]},{"text":"这个现行反革命分子刘镇美就是隐瞒","box":[[2080,3065],[2571,3081],[2569,3127],[2079,3111]]},{"text":"个文件时发现的。”并立即从口袋里拿出来","box":[[254,3086],[789,3102],[788,3134],[253,3118]]},{"text":"与她自己所讲口径不一致：大家对她怀疑","box":[[1435,3085],[1972,3101],[1971,3133],[1434,3117]]},{"text":"分析。从排队到排队，挖空心思找线索，","box":[[839,3109],[1365,3119],[1364,3155],[838,3146]]},{"text":"成份，自称贫农出身，老党员、老干部、","box":[[2021,3101],[2556,3122],[2554,3163],[2019,3142]]},{"text":"给尹××看，要他一道去报案。此反动标","box":[[252,3121],[792,3137],[791,3172],[251,3156]]},{"text":"越来越大。就在这种情况下，破案领导小","box":[[1432,3123],[1970,3137],[1969,3169],[1431,3155]]},{"text":"对笔迹，立靶子。如此冷冷清清地搞，始","box":[[838,3146],[1379,3157],[1378,3193],[837,3182]]},{"text":"老革命、地委特派书记的地主封建剥削阶","box":[[2021,3138],[2569,3157],[2568,3203],[2019,3183]]},{"text":"语是写在某首长讲话的传单上，其矛头是","box":[[254,3162],[787,3177],[786,3209],[253,3194]]},{"text":"组根据广大革命群众的要求，对她实行隔","box":[[1429,3158],[1970,3174],[1969,3209],[1428,3193]]},{"text":"终得不到一个结果，最后就一拖再拖，不","box":[[838,3181],[1380,3192],[1379,3233],[837,3222]]},{"text":"级的孝子贤孙。这个混蛋当文化大革命运","box":[[2018,3174],[2572,3195],[2571,3241],[2016,3220]]},{"text":"离审查，使这个现行反革命分子落入“人","box":[[1428,3194],[1970,3212],[1969,3248],[1427,3231]]},{"text":"直指我们最最敬爱的伟大领袖毛主席和林","box":[[252,3205],[787,3221],[786,3253],[251,3237]]},{"text":"动一开始，就操纵扶植保守势力，打击造","box":[[2017,3212],[2572,3233],[2571,3279],[2015,3258]]},{"text":"了了之。","box":[[843,3223],[943,3223],[943,3257],[843,3257]]},{"text":"副主席、周总理，真是反动透顶！除了两条","box":[[255,3243],[787,3259],[786,3291],[254,3275]]},{"text":"民战争”的汪洋大海之中。","box":[[1431,3235],[1778,3243],[1777,3275],[1430,3267]]},{"text":"然面，当时公司不少革命群众知道此","box":[[898,3260],[1377,3268],[1377,3303],[898,3295]]},{"text":"反派，在二月反革命逆流中，她又残酷镇","box":[[2018,3252],[2569,3273],[2568,3315],[2016,3295]]},{"text":"极反动的标语外，同时还有一条“捣毁刘家","box":[[255,3279],[787,3297],[786,3329],[254,3311]]},{"text":"为了让这个现行反革命分子暴露得更","box":[[1487,3273],[1967,3286],[1966,3318],[1486,3305]]},{"text":"现行反革命案件后，怀着对我们伟大领袖","box":[[839,3295],[1379,3304],[1378,3341],[838,3331]]},{"text":"压群众运动，大整革命群众的黑材料，把","box":[[2018,3290],[2569,3311],[2568,3353],[2016,3333]]},{"text":"彻底，破案领导小组和广大革命群众又采","box":[[1426,3307],[1970,3323],[1969,3359],[1425,3343]]},{"text":"店，杀死刘镇美！”的标语，上面“刘”字写","box":[[254,3317],[787,3335],[786,3367],[253,3349]]},{"text":"毛主席的无限忠诚，对阶级敌人的无比仇","box":[[839,3331],[1376,3342],[1375,3379],[838,3368]]},{"text":"不少革命造反派打成“反革命”，“牛鬼","box":[[2017,3325],[2568,3347],[2566,3393],[2015,3370]]},{"text":"成“刘”字，镇字写成“”。尹××看","box":[[252,3356],[787,3373],[786,3405],[251,3387]]},{"text":"取了一系列重大措施。","box":[[1428,3348],[1708,3355],[1707,3387],[1427,3380]]},{"text":"恨，议论纷纷，多次向旧公安处提出要","box":[[839,3369],[1379,3380],[1378,3415],[838,3404]]},{"text":"蛇神”，顽固地执行资产阶级反动路","box":[[2017,3363],[2571,3385],[2569,3431],[2015,3409]]},{"text":"第一，进行了群众性的审讯，要报案者","box":[[1482,3384],[1969,3399],[1968,3434],[1481,3419]]},{"text":"后，两人就一同到公安处去报案。在路上","box":[[254,3394],[786,3409],[785,3441],[253,3426]]},{"text":"求打人民战争，发动群众破案。可是旧公","box":[[839,3407],[1377,3418],[1376,3453],[838,3442]]},{"text":"线。","box":[[2018,3408],[2068,3408],[2068,3436],[2018,3436]]},{"text":"把过去报案经过再详细叙述，每一造反队","box":[[1428,3419],[1967,3435],[1966,3472],[1427,3456]]},{"text":"她似乎很有把握地讲：“可能会不会是小孩","box":[[251,3430],[789,3446],[788,3481],[250,3465]]},{"text":"安处无视我公司广大革命群众的强烈要","box":[[839,3442],[1377,3455],[1376,3492],[838,3479]]},{"text":"刘镇美这个现行反革命分子揪出来","box":[[2076,3444],[2566,3461],[2565,3502],[2074,3485]]},{"text":"都同样进行，给她来了个措手不及。群众在","box":[[1426,3457],[1966,3473],[1965,3510],[1425,3494]]},{"text":"子趁开门时放进去的”，同时忽然又要求","box":[[254,3468],[786,3484],[785,3516],[253,3500]]},{"text":"求，结果使这个罪大恶极的现行反革命分","box":[[836,3480],[1374,3491],[1373,3528],[835,3517]]},{"text":"了！这是毛主席革命路线的伟大胜利，是","box":[[2020,3479],[2566,3499],[2565,3542],[2018,3521]]},{"text":"审讯中发现她每讲一次，所讲到不少重要","box":[[1426,3495],[1967,3511],[1966,3548],[1425,3532]]},{"text":"XX一人去报案。尹Xx认为刘是当事","box":[[252,3506],[787,3523],[786,3555],[251,3538]]},{"text":"子逍遥法外。","box":[[840,3520],[1006,3527],[1005,3559],[838,3552]]},{"text":"毛泽东思想的伟大胜利，是伟大的中国人","box":[[2016,3518],[2562,3536],[2560,3578],[2015,3561]]},{"text":"关节都不一致，神态也相当谎张。如一次","box":[[1425,3532],[1967,3549],[1966,3586],[1424,3568]]},{"text":"人，一定要两人一同去。两人到了公安","box":[[254,3544],[787,3562],[786,3593],[253,3576]]},{"text":"民解放军三支两军的丰功伟绩，是领导，","box":[[2015,3555],[2548,3574],[2547,3615],[2013,3596]]},{"text":"在审讯她时，她突然见到解放军同志，","box":[[1423,3568],[1949,3586],[1948,3622],[1422,3605]]},{"text":"处，刘介绍了发现案件经过。旧公安处人","box":[[252,3582],[787,3596],[786,3628],[251,3614]]},{"text":"阶级敌人原形毕露","box":[[957,3579],[1285,3584],[1284,3621],[957,3616]]},{"text":"专业人员、群众三结合破案的辉煌成果，","box":[[2015,3593],[2545,3612],[2544,3653],[2013,3634]]},{"text":"立即慌张起来，叫她读毛主席语录，她","box":[[1423,3606],[1966,3625],[1965,3660],[1422,3641]]},{"text":"员表示派人来观察现场。","box":[[251,3620],[563,3628],[562,3660],[250,3652]]},{"text":"在省革委会主要负责同志的直接指示","box":[[897,3636],[1374,3647],[1373,3679],[896,3667]]},{"text":"充分显示了人民战争和群众专政的强大威","box":[[2015,3631],[2562,3648],[2560,3689],[2013,3672]]},{"text":"手里明明拿着毛主席语录，却谎得讲","box":[[1422,3646],[1966,3663],[1965,3698],[1421,3681]]},{"text":"力。","box":[[2014,3674],[2061,3674],[2061,3703],[2014,3703]]}],"dimensions":{"height":3797,"width":2669}}