{"ocr_results":[{"text":"戏剧战报","box":[[710,153],[926,156],[926,186],[710,183]]},{"text":"1967年6月24日","box":[[1286,169],[1442,162],[1443,187],[1287,195]]},{"text":"我到我報","box":[[1612,162],[2367,131],[2379,418],[1624,448]]},{"text":"国家的统一，人民的团","box":[[2526,211],[2822,214],[2822,239],[2526,236]]},{"text":"陶、林默涵、齐燕铭、田汉、阳翰笙在广州黑会上的部分黑話摘编","box":[[256,233],[1373,233],[1373,272],[256,272]]},{"text":"结，国内各民族的团结，这","box":[[2463,260],[2826,261],[2826,290],[2463,289]]},{"text":"中国剧协苹命造反团中国剧协《长缦在手》造反队","box":[[587,296],[1052,297],[1052,318],[587,317]]},{"text":"是我们的事业必定要胜利的","box":[[2466,313],[2827,313],[2827,337],[2466,337]]},{"text":"[按]：反苹命两面派陶铸、活阁王林欧涵、前文化部副部长齐燕铭、前中国戏剧家协会主席田汉、前全国文","box":[[364,344],[1311,347],[1311,371],[363,368]]},{"text":"联副主席阳翰笙等一小摄党内走资本主义道路的当权派、反苹命修正主义分子，在他们的黑主子刘少奇的支持和","box":[[325,369],[1313,371],[1313,396],[325,395]]},{"text":"基本保证。","box":[[2464,361],[2604,364],[2603,389],[2463,386]]},{"text":"鼓励下，于1962年3月在广州召开的所谓“全国话剧、歌剧、儿童剧创作座谈会”上，为了达到他们复辟资本主义","box":[[324,393],[1311,397],[1311,421],[324,417]]},{"text":"的罪恶目的，以“报告”为名，大讲黑话，向党向社会主义向毛泽东思想，进行了狂的进攻，安图颠复无产阶级","box":[[325,420],[1313,421],[1313,445],[325,444]]},{"text":"主办单位：中 国 剧 协 革 命 造反 团 紅代会中央戏剧学院紅旗文艺兵团","box":[[1647,417],[2347,414],[2347,443],[1647,446]]},{"text":"太源东","box":[[2667,421],[2788,421],[2788,459],[2667,459]]},{"text":"专政，改变我们佛大的社会主义国家的颜色。现将他们黑“报告”中的部分黑话，摘编示众，供革命派战友们批判。","box":[[325,444],[1310,446],[1310,470],[325,468]]},{"text":"中国青年艺术剧院东方红总部剧协北京分会革命造 反队","box":[[1748,449],[2347,444],[2348,472],[1749,477]]},{"text":"第四期共四版","box":[[1788,487],[1997,487],[1997,507],[1788,507]]},{"text":"1967年6月24日","box":[[2027,486],[2196,484],[2197,506],[2028,507]]},{"text":"欣赏。","box":[[612,495],[662,495],[662,512],[612,512]]},{"text":"看起来，这很可笑。","box":[[1058,494],[1204,497],[1204,517],[1058,514]]},{"text":"陶的黑话","box":[[282,517],[467,514],[467,540],[283,542]]},{"text":"△修正主义者只承认生活都是黑暗，不承认生活里","box":[[644,516],[1030,516],[1030,536],[644,536]]},{"text":"△我们請头哈同志组过八十个历史题材的书，印出","box":[[1088,517],[1461,513],[1461,537],[1088,541]]},{"text":"而有光明。那么我们反过来只写光明，不写生活里的候","box":[[611,539],[1031,539],[1031,559],[611,559]]},{"text":"来可奉送各位，写历史剧請历史学家帮助我们会有好处","box":[[1053,537],[1461,536],[1461,560],[1053,561]]},{"text":"△我们有些同志一脸的秋风萧恋”，那怎么能百花","box":[[200,563],[585,558],[586,577],[201,582]]},{"text":"点，生活里的阴暗面，这是叉走到另一个极路。","box":[[610,562],[970,562],[970,579],[610,579]]},{"text":"的。","box":[[1055,561],[1082,561],[1082,580],[1055,580]]},{"text":"分清敌我牢牢掌握斗争大方向","box":[[1774,557],[2725,555],[2725,608],[1774,609]]},{"text":"齐放，百家拿鸣呢，我看肃杀之气太甚了。也许我讲的","box":[[165,585],[582,580],[582,601],[166,606]]},{"text":"△任何时候都可以对作品有各种各样的看法，问题","box":[[644,582],[1030,583],[1030,603],[644,602]]},{"text":"△我们来时是阴天，回去后该天晴了。晴天是经常","box":[[1090,584],[1457,582],[1458,603],[1090,606]]},{"text":"會过共实了，但至少现在不是温吸的春天，说得好一","box":[[168,607],[584,603],[585,624],[168,627]]},{"text":"在于从教条主义出发，还是从作品的实际出发，《布谷","box":[[609,603],[1029,604],[1029,625],[609,624]]},{"text":"状态，阴天是暂时的，它很快就会过去。中国共产党社","box":[[1055,606],[1460,606],[1460,626],[1055,626]]},{"text":"点，也只不过是早春天气，乍还寒时候。我总希","box":[[168,631],[586,626],[586,645],[168,650]]},{"text":"乌叉叫了》我觉得是个应该基本上肯定、本上是好的","box":[[609,626],[1029,627],[1029,648],[609,646]]},{"text":"会主义耻会制度是晴的，但也不要否认有阴的现象，扫","box":[[1055,628],[1461,628],[1461,649],[1055,649]]},{"text":"作品，好的喜刚。","box":[[610,651],[738,651],[738,668],[610,668]]},{"text":"除阴福，各地区需要很大努力。","box":[[1053,649],[1289,651],[1288,672],[1053,669]]},{"text":"一記念《关于正确处理人民内部矛盾的问题》发表十周年","box":[[1937,642],[2596,638],[2596,661],[1937,664]]},{"text":"望，我们不要再刮秋风了，多刮一点温吸的春风吧。秋","box":[[168,652],[584,648],[585,669],[168,674]]},{"text":"风一来，树叶尽脱，还有什么百花齐放呢。","box":[[168,674],[490,672],[490,692],[168,694]]},{"text":"△好的戏，中外古今要搞一些，戏刷理论也应系统","box":[[642,672],[1028,672],[1028,692],[642,692]]},{"text":"的出来，《汉堡剧评》都没有完全翻出来。我们有知","box":[[606,693],[1028,694],[1028,715],[606,714]]},{"text":"·本报编辑部·","box":[[2171,686],[2319,684],[2320,705],[2171,708]]},{"text":"△政权实在是十分重要的呵，但我们也要看到，它","box":[[203,698],[585,692],[586,712],[203,719]]},{"text":"田汉的黑話","box":[[1170,696],[1350,696],[1350,721],[1170,721]]},{"text":"也有它的缺点，运用得不好，可以使我们滋长官像主","box":[[169,721],[587,716],[587,735],[169,740]]},{"text":"识，怎么行！","box":[[609,715],[707,717],[706,738],[608,735]]},{"text":"今年六月十九日，是我们最最敬爱的伟大领袖毛主席的伟大落作《关教导：“在我們的面前有两类社会矛盾，这就是敌我之間的矛盾和人民内部","box":[[1630,730],[2909,732],[2909,756],[1630,754]]},{"text":"义，股离群众，可以使我们利用政权来搞特殊化。刀可","box":[[169,741],[583,738],[583,759],[169,763]]},{"text":"△有次乔木同志跟夏衍同志谈话，乔木同志说，话","box":[[645,740],[1028,740],[1028,757],[645,757]]},{"text":"△去年文化部、宣传部召开的文艺工作座谈会合经","box":[[1083,741],[1459,741],[1459,758],[1083,758]]},{"text":"以杀强盗，但是也可以杀自己。","box":[[168,764],[403,763],[403,783],[168,784]]},{"text":"喇为什么发展不够繁荣，创作不够旺盛，什么道理”，后","box":[[612,763],[1026,763],[1026,780],[612,780]]},{"text":"谈过一些问题，纠正了一些福向，但是不够彻底。同志","box":[[1053,762],[1459,762],[1459,782],[1053,782]]},{"text":"于正确处理人民内部矛后的问题》发表十周年的光辉节日。","box":[[1590,758],[2094,760],[2094,781],[1590,778]]},{"text":"的矛盾。这是性質完全不同的两类矛盾。”“敌我之間和人民内部这两类矛","box":[[2257,758],[2907,757],[2907,781],[2257,782]]},{"text":"△要跟着共产党走，不是跟着那个人走。","box":[[203,787],[503,783],[504,804],[203,807]]},{"text":"米他又这样说：“大概管的人太多了。”这儿年来，有一","box":[[607,782],[1024,783],[1024,804],[607,802]]},{"text":"们出了一些气，但是没有出完，还有点情绪，不那么舒","box":[[1055,784],[1457,784],[1457,805],[1055,805]]},{"text":"毛主席在这篇伟大茗作中，科学地总结了我国和国际无产阶级革命和盾的性質不同，解决的方法也不同。”这样，我们才能正确区分和正确处理","box":[[1629,782],[2910,783],[2910,807],[1629,806]]},{"text":"△关于大炼铁，铜铁的速度问题，也是性急了些。","box":[[204,810],[572,807],[572,826],[204,829]]},{"text":"門是比较好的，这就是木刻、版画，为什么这一門好呢？","box":[[606,805],[1018,806],[1018,826],[606,825]]},{"text":"畅。希望在这次会上大家把气一吐为快。","box":[[1052,805],[1356,806],[1356,826],[1052,825]]},{"text":"无产阶级专政的历史经验，在马克思主义发展史上第一次天才地、科学地、","box":[[1590,808],[2261,811],[2260,831],[1590,829]]},{"text":"两类不同性质的矛盾，分清敌我，明辨是非，牢牢学握斗争的大方向，把","box":[[2251,811],[2909,811],[2909,831],[2251,831]]},{"text":"△这两年我们不能怪下面，有些方面我们搞“左”","box":[[204,831],[573,829],[574,849],[204,852]]},{"text":"就是这一凹没人管，谁都不管它，它就发展得好了，管","box":[[607,826],[1026,828],[1026,848],[607,847]]},{"text":"△特别是人民性的问题还是要看宽一点的好，太狭","box":[[1088,829],[1457,829],[1457,849],[1088,849]]},{"text":"系统地、深刘地分析了社会主义社会的矛盾、阶级和阶级斗伞，提出了正矛头对准以刘少奇为首的党内一小报走资本主义道路的当权派，彻底清算","box":[[1592,834],[2908,836],[2908,858],[1592,855]]},{"text":"了，有些运动搞的过火了。…你经常整得人家失掉了","box":[[170,853],[581,853],[581,873],[170,873]]},{"text":"得最多的就植糕。","box":[[607,849],[756,848],[756,868],[607,870]]},{"text":"了。我们认为只要对人民没有坏处的健康的就行了，","box":[[1053,849],[1453,852],[1453,872],[1053,869]]},{"text":"确区分和正确处理两类不同性质的矛盾的英明论断，创造性地继承和发展他们的一切罪行，把他们斗倒、斗垮、斗臭。同时，我们才能在革命的大","box":[[1589,858],[2909,859],[2909,883],[1589,882]]},{"text":"信心，还认为斗争人家是党性很强，很坚决，但很少考","box":[[169,876],[583,874],[583,895],[169,896]]},{"text":"△必须保证作家的个人创造性，个人的爱好。………","box":[[642,871],[1024,868],[1024,892],[643,895]]},{"text":"就可以肯定了。把門开得大一些。人民性不一定都有战","box":[[1048,872],[1459,874],[1459,895],[1048,892]]},{"text":"了马列主义关于无产阶级革命和无产阶级专政的学说。毛主席的这篇光辉批判中，用“团结一一批评一一团结”的方法解决人民内部矛盾，使一切革","box":[[1593,883],[2910,884],[2910,908],[1593,907]]},{"text":"虑人家被斗后是多么痛苦。","box":[[169,898],[368,898],[368,919],[169,919]]},{"text":"也可以向作家提出一些要求，但只是要求而已，千万不","box":[[609,893],[1028,895],[1028,915],[609,914]]},{"text":"斗性。山水持，风花雪月也可以肯定下来。","box":[[1054,897],[1377,897],[1377,914],[1054,914]]},{"text":"要她强。作家到底要写什么，完全由作家自已决定，任","box":[[606,916],[1026,918],[1026,938],[606,937]]},{"text":"△但要把革命旗帜举起米，就扳起面孔，股高郡","box":[[1088,916],[1459,918],[1459,939],[1088,938]]},{"text":"著作的发表，是对马列主义理论的最伟大贡献，在实践中，从根本上解决 命同志和革命组织在毛泽东思想的伟大红旗下，团结起来，联合起来，为","box":[[1590,908],[2910,912],[2910,936],[1590,932]]},{"text":"△不要动不动就划人家右派分子。大家都是来","box":[[203,920],[583,920],[583,940],[203,940]]},{"text":"何人不可以勉强。","box":[[609,938],[737,940],[736,961],[608,958]]},{"text":"众，路子越走越窄，弄得人家不看，也是不好的。所以","box":[[1052,937],[1460,939],[1460,963],[1052,961]]},{"text":"了如何在无产阶级专政条件下进行革命的问题。它在我国革命发展史上和","box":[[1593,932],[2244,934],[2244,958],[1593,956]]},{"text":"革命的嘛，人同此心，心同此理，我看除了极少数人","box":[[168,943],[582,941],[582,962],[168,963]]},{"text":"完成斗批改的光荣任务而战斗。","box":[[2256,938],[2539,938],[2539,958],[2256,958]]},{"text":"外，谁个不想把我们的国家搞好呵！","box":[[170,967],[437,967],[437,983],[170,983]]},{"text":"△作家顾虑很多，这个一个时期以来缺少民主生","box":[[644,963],[1025,963],[1025,980],[644,980]]},{"text":"要放松为革命服务的尺度。","box":[[1054,964],[1253,964],[1253,981],[1054,981]]},{"text":"国际共产主义运动发展史上，是一篇划时代的的马列主义的历史文献。","box":[[1590,959],[2213,961],[2213,981],[1590,980]]},{"text":"只有好好地学习毛主席的这篇不朽若作，我们才会永远牢记毛主席的","box":[[2300,961],[2909,959],[2909,983],[2300,985]]},{"text":"△这两三年来，大家物质生活已经相当苦了，没有","box":[[203,988],[582,986],[582,1005],[203,1008]]},{"text":"活的空气也有关系，这不光是文艺工作的问题。缺乏民","box":[[609,986],[1024,986],[1024,1003],[609,1003]]},{"text":"△有大讲，斯大林就是很大的悲剧。这个伟大的马","box":[[1088,983],[1458,986],[1457,1006],[1088,1004]]},{"text":"对于这样一篇伟大的作，我们必须天天学，月月学，年年学，永远","box":[[1629,982],[2245,985],[2245,1009],[1629,1006]]},{"text":"教导，“世界观的轉变是一个根本的轉变，現在多数知识分子还不能已","box":[[2235,988],[2907,988],[2907,1009],[2235,1009]]},{"text":"猪肉吃，没有烟抽，再加上精神上受虐待，那怎么还","box":[[170,1011],[582,1011],[582,1028],[170,1028]]},{"text":"主生活，在生活中不讲宾话，文学艺术反而能讲真话？","box":[[606,1005],[1018,1007],[1018,1028],[606,1025]]},{"text":"列主义者，一到晚年股离群众，影响很大，犯了很大的","box":[[1048,1005],[1459,1007],[1459,1029],[1048,1027]]},{"text":"学特别是现在，我国的无产阶级文化大苹命正处于一个崭新的阶段，我","box":[[1592,1009],[2246,1010],[2246,1034],[1592,1033]]},{"text":"经完成了这个轉变。”这样，我们就能在伟大的无产阶级文化大革命中，在","box":[[2257,1012],[2910,1012],[2910,1036],[2257,1036]]},{"text":"能创作出好的作品来呢。","box":[[171,1034],[348,1034],[348,1051],[171,1051]]},{"text":"这怎么可能：你要讲，便整你了，戴帽子。不讲真话是","box":[[604,1028],[1026,1029],[1026,1049],[604,1048]]},{"text":"错误，是个很大的悲刷。","box":[[1053,1030],[1234,1030],[1234,1047],[1053,1047]]},{"text":"们重温毛主席《关于正确处理人民内部矛盾的问题》的教导，具有特别重大","box":[[1590,1034],[2245,1035],[2245,1059],[1590,1058]]},{"text":"三大革命运动的实践中，自觉地改造自己，不断触及自己的灵魂，大破私","box":[[2238,1037],[2911,1036],[2911,1060],[2238,1061]]},{"text":"△现在情况怎样呢？一方面，作家本身可能有些问","box":[[203,1054],[583,1054],[583,1075],[203,1075]]},{"text":"个大问题。","box":[[606,1051],[690,1051],[690,1071],[606,1071]]},{"text":"△英雄都是有缺点的。天下没有“完人”，完人就完","box":[[1086,1048],[1460,1052],[1460,1076],[1085,1072]]},{"text":"△大家不想干了，要改行了，这还是领导正确？不","box":[[642,1072],[1026,1073],[1026,1094],[642,1093]]},{"text":"蛋了。…….写人物不要坏的尽坏，好的尽是好。","box":[[1050,1071],[1402,1076],[1402,1096],[1049,1091]]},{"text":"的现实意义和深远意义。","box":[[1591,1063],[1815,1060],[1815,1081],[1592,1083]]},{"text":"学，大立公字，努力实现自已思想革命化，把自己培养成为毛主席的好战士。","box":[[2259,1063],[2910,1061],[2910,1085],[2259,1087]]},{"text":"题；另方面，我们搞得人家心情很不舒畅，怎么能使人","box":[[170,1078],[581,1078],[581,1095],[170,1095]]},{"text":"是越写越想写，而是越写越不想写，自已要改行，而且","box":[[608,1094],[1025,1097],[1025,1118],[607,1114]]},{"text":"△评一个人恐怕要分段，不要因后一段不好，就","box":[[1085,1092],[1462,1099],[1462,1123],[1084,1116]]},{"text":"只有好好地学习毛主席的这篇光辉著作，我们才会永远半记毛主席的","box":[[1633,1085],[2240,1085],[2240,1109],[1633,1109]]},{"text":"无产阶级革命派任重而道远。为了把我国的革命进行到底，为了把毛","box":[[2302,1088],[2911,1087],[2911,1111],[2302,1112]]},{"text":"家对社会主义有丰富的成情呢，……搞得人家心情不舒","box":[[167,1099],[582,1099],[582,1119],[167,1119]]},{"text":"对儿女说今后不要干这事情了。这样子的领导就是伤","box":[[606,1117],[1024,1118],[1024,1139],[606,1138]]},{"text":"统统否定他的前一段。段就增在“三一八”时期银坏，有","box":[[1050,1114],[1462,1120],[1462,1144],[1049,1138]]},{"text":"教导，“在我国，虽然社会主义改造，在所有制方面来，已经基本完成”，","box":[[1589,1109],[2241,1111],[2241,1136],[1589,1135]]},{"text":"泽东思想伟大红旗插逼全球，我们必须把学习、掌握、宣传、捍卫毛泽东","box":[[2253,1113],[2913,1112],[2913,1136],[2253,1137]]},{"text":"畅，反过来还要求人家歌颈社会主义，对社会主义有深","box":[[167,1123],[582,1123],[582,1139],[167,1139]]},{"text":"厚的或情，这也国难了。","box":[[170,1145],[374,1145],[374,1162],[170,1162]]},{"text":"积极性，甚至想自杀，这说明领导失败，我们不要这样","box":[[608,1139],[1028,1143],[1027,1163],[607,1160]]},{"text":"人讲，他个人的品德还有好处，这是可能的。","box":[[1048,1138],[1385,1142],[1385,1166],[1048,1162]]},{"text":"但是“阶极斗争井有精束。无产阶級和资产阶级之間的阶級斗争，各派","box":[[1592,1137],[2246,1136],[2246,1160],[1592,1161]]},{"text":"思想放在高于一切、大于一以、先于一切、重于一切的位置上。戏剧界无","box":[[2238,1138],[2913,1137],[2913,1162],[2238,1163]]},{"text":"的领导，要正确的领导，领导还是要的。","box":[[607,1162],[913,1165],[913,1184],[607,1181]]},{"text":"△活剧是从西洋学来的·搞来搞去就是一个《娜","box":[[1085,1158],[1461,1166],[1461,1190],[1084,1182]]},{"text":"△这几年的创作更加有些菱缩了，首路更常了。","box":[[204,1168],[578,1168],[578,1184],[204,1184]]},{"text":"政治力量之間的阶級斗争，无产阶级和资产阶級之間在意识形态方面的阶","box":[[1593,1162],[2246,1162],[2246,1186],[1593,1186]]},{"text":"产阶级革命派的战友们，革命的同志们，让我们用“只争朝夕”的革命精","box":[[2233,1163],[2911,1162],[2911,1187],[2233,1189]]},{"text":"为什么会这样：这和我们领导文艺工作的部門和同志不","box":[[169,1190],[582,1190],[582,1207],[169,1207]]},{"text":"△有人说，三个人在一起讲的话都是假的，两个人","box":[[642,1185],[1024,1187],[1024,1208],[642,1205]]},{"text":"拉》。莎士比亚的戏也就是一个《罗密欧与朱丽叶》。这","box":[[1048,1181],[1461,1189],[1461,1213],[1048,1205]]},{"text":"极斗争，还是长时期的，曲折的，有时甚至是很激烈的。”这样，我们就会","box":[[1594,1190],[2250,1190],[2250,1210],[1594,1210]]},{"text":"神，活学活用毛主席著作，积极投入到当前森淼烈烈的革命的大批判大斗","box":[[2258,1189],[2911,1187],[2911,1213],[2258,1214]]},{"text":"拿重创作的“所有权”，不重拿作家，干预太多，路指挥","box":[[169,1213],[583,1213],[583,1229],[169,1229]]},{"text":"在一起讲的是中真半假，只有一个人自已讲的才是真","box":[[606,1206],[1026,1210],[1026,1231],[606,1227]]},{"text":"是一个国耻。","box":[[1049,1210],[1146,1210],[1146,1227],[1049,1227]]},{"text":"念念不忘阶级斗分，念念不忘无产阶级专政，坚决把革命进行到底。","box":[[1593,1214],[2210,1211],[2210,1235],[1593,1238]]},{"text":"△对欧洲的东西一无所知，我们太关門了。……这","box":[[1082,1224],[1461,1232],[1461,1259],[1082,1252]]},{"text":"争中去，把党内最大的一小报走资本主义道路当权派斗倒斗均斗臭，把无","box":[[2262,1215],[2911,1214],[2911,1239],[2262,1240]]},{"text":"等有很大关系。","box":[[168,1230],[286,1233],[286,1253],[168,1251]]},{"text":"的。","box":[[607,1229],[635,1229],[635,1249],[607,1249]]},{"text":"说明我们有礼貌，资有耐性，没有雅量，很浅薄，心","box":[[1047,1246],[1461,1256],[1461,1284],[1047,1274]]},{"text":"只有好好地学习毛主席的这篇伟大著作，我们才会永远牢记毛主席的","box":[[1634,1239],[2246,1238],[2246,1262],[1634,1263]]},{"text":"产阶级文化大革命进行到底！","box":[[2234,1240],[2519,1245],[2519,1265],[2234,1260]]},{"text":"△个后做领导工作的，再也不要抓器子，不要乱干","box":[[200,1257],[582,1257],[582,1274],[200,1274]]},{"text":"△有人提这搞一些内部参考小说，他们很气慎，这","box":[[643,1250],[1024,1255],[1024,1275],[642,1270]]},{"text":"S","box":[[185,1261],[201,1259],[202,1269],[186,1270]]},{"text":"个不能说，那个不能说，是不是可以山内部参考小说。","box":[[605,1274],[1013,1277],[1013,1297],[605,1293]]},{"text":"底很窄狭，孤随寨间，就指这一个东西吃到底（按：指","box":[[1047,1269],[1463,1279],[1462,1306],[1047,1296]]},{"text":"涉，不要踏指挥，要使作家写自已宾正体验、取受到的","box":[[169,1279],[582,1279],[582,1295],[169,1295]]},{"text":"东西，不要学韩复的文亲，叫人家演关公火战秦琼”","box":[[168,1300],[570,1300],[570,1317],[168,1317]]},{"text":"△首先要向中国老作家学习，向田老、老合、曹禺、","box":[[644,1296],[1013,1299],[1013,1319],[644,1317]]},{"text":"毛主席《在延安文艺座谈会上的讲话》），已经快吃完了，","box":[[1049,1293],[1454,1303],[1453,1328],[1048,1318]]},{"text":"阳愉老、欧阳老学习共次，是向戏曲传统学习，第","box":[[608,1318],[1025,1322],[1025,1342],[607,1338]]},{"text":"还啃这个东西。…要打开大門，吸收新鲜空气！我们","box":[[1046,1313],[1461,1324],[1461,1353],[1045,1342]]},{"text":"一个触目惊心的反革命复辟事件","box":[[1795,1311],[2742,1316],[2742,1369],[1794,1364]]},{"text":"作为作家，就是要具正写自已所体验、所成受的东西。","box":[[169,1322],[575,1322],[575,1342],[169,1342]]},{"text":"△违反创作规律的事，还是少来一些吧，还是拿重","box":[[203,1346],[582,1346],[582,1362],[203,1362]]},{"text":"三，我觉得还是要向外国学习，包括资本主义国家，费","box":[[608,1341],[1026,1345],[1026,1366],[607,1362]]},{"text":"保守得够赠了！","box":[[1049,1344],[1165,1344],[1165,1361],[1049,1361]]},{"text":"作家，叫人家创作自由吧。不如此，是没法紧装创作","box":[[167,1365],[583,1366],[583,1386],[167,1385]]},{"text":"本主义国家在戏剧上确实找寻新的手法。","box":[[606,1364],[913,1369],[913,1389],[606,1384]]},{"text":"的。","box":[[168,1389],[198,1389],[198,1407],[168,1407]]},{"text":"△我提议把中国古典的、外国古典的东西组一套资","box":[[641,1388],[1023,1391],[1023,1412],[641,1408]]},{"text":"阳翰笙的黑话","box":[[1148,1386],[1367,1393],[1366,1418],[1147,1411]]},{"text":"揭开广州黑会的黑幕","box":[[2098,1381],[2456,1389],[2456,1417],[2097,1409]]},{"text":"△唐明皇是个封肆帝王，他为了讨得一个妃子的欢","box":[[203,1413],[582,1413],[582,1430],[203,1430]]},{"text":"料，有代表性的，从希腊悲剧到契夫。最近，李健吾","box":[[606,1409],[1024,1414],[1024,1435],[606,1430]]},{"text":"心，还对李白那么拿重。现在我们是希望写出人民欢迎","box":[[168,1432],[582,1434],[582,1454],[168,1451]]},{"text":"同志组了一本书叫《欧洲戏刚理论汇组》，从亚里士多德","box":[[604,1431],[1025,1436],[1025,1459],[604,1454]]},{"text":"△在领导创作违背了创作规律这个问题上，还制遗","box":[[1083,1423],[1463,1437],[1462,1466],[1082,1452]]},{"text":"中国剧协苹命造反团中国剧协《长在手》造反队","box":[[2019,1433],[2495,1441],[2495,1465],[2019,1457]]},{"text":"的好东西，为什么对作家不算重呢！《西游记》不是有个","box":[[168,1454],[582,1457],[582,1476],[168,1473]]},{"text":"到宵伯纳，有百多万字，将来出版最好能够人手一册。","box":[[605,1455],[1019,1460],[1019,1480],[605,1475]]},{"text":"了许多柜，有下面这么十条框框：“否定创作规律”；","box":[[1034,1447],[1459,1459],[1458,1487],[1033,1476]]},{"text":"唐借和孙悟空吗，孙情空对待唐借取经不是忠心联联","box":[[167,1476],[582,1480],[582,1499],[167,1496]]},{"text":"“强调有生活，就是干劲不足”；“否定创作需要才能”；","box":[[1048,1470],[1454,1483],[1453,1510],[1047,1498]]},{"text":"“否定艺术规律”；“领导定题、定人、定时、定量”；“三","box":[[1045,1490],[1464,1506],[1463,1534],[1044,1519]]},{"text":"一九六二年一月，党内最大的走资本主义道就是身名昭著，流毒全国的广州黑会。现在，是","box":[[1631,1481],[2477,1485],[2477,1518],[1631,1515]]},{"text":"吗，唐借遇事就应该与孙悟尘商量吗，但是，他不崇商","box":[[167,1498],[582,1500],[582,1521],[167,1518]]},{"text":"齐燕銘的黑话","box":[[703,1499],[928,1504],[927,1529],[703,1524]]},{"text":"广州黑会从准备阶段起，始终是在旧中宣","box":[[2533,1493],[2912,1485],[2913,1509],[2534,1517]]},{"text":"结合”；“只要抓住重大题材”；“写尖端人物（按：指英","box":[[1046,1513],[1464,1528],[1463,1557],[1045,1542]]},{"text":"路当权派刘少奇，抛出了一个反党反社会主义的，彻底清算达次大黑会，彻底肃清共一切流毒的时","box":[[1589,1504],[2483,1506],[2483,1551],[1589,1548]]},{"text":"量，他靠着紧槟咒。","box":[[167,1520],[318,1521],[317,1541],[167,1540]]},{"text":"部、旧文化部一小报反革命修正主义头头周扬、","box":[[2470,1522],[2904,1512],[2904,1533],[2471,1543]]},{"text":"△这几年搞运动，大家都很紧张。运动还是要搞，","box":[[201,1542],[571,1545],[571,1565],[200,1563]]},{"text":"△我们在延安搞《通上梁山》，解放后演，原因觉得","box":[[642,1545],[1026,1547],[1026,1568],[642,1565]]},{"text":"雄人物）”；“强调写其人其事”：“否定艺术创作个体劳","box":[[1045,1536],[1464,1551],[1463,1580],[1044,1565]]},{"text":"黑报告。这个中国的楼鲁晓夫，大肆叫什么：“不","box":[[1591,1544],[2023,1534],[2024,1558],[1592,1568]]},{"text":"候了！","box":[[2018,1540],[2097,1540],[2097,1560],[2018,1560]]},{"text":"林默涵、夏行、齐燕铭、徐平羽、田汉、阳愉笙","box":[[2492,1545],[2915,1536],[2915,1560],[2493,1569]]},{"text":"但主要是自我改造。个后不搞运动或少搞运动。","box":[[167,1564],[582,1568],[582,1588],[167,1584]]},{"text":"它不成熟。…第一强训艺术地表现群众力量，群众是","box":[[608,1565],[1023,1569],[1023,1592],[607,1588]]},{"text":"动的特点”。…这十条就成丁十条绳子，就把咱们捆","box":[[1046,1559],[1463,1574],[1462,1603],[1045,1588]]},{"text":"要作那一种股离实际的，脱高群众的，冒里冒失","box":[[1593,1569],[2022,1559],[2023,1584],[1593,1594]]},{"text":"一个精心策划的反党大黑会","box":[[2141,1578],[2380,1585],[2380,1609],[2141,1602]]},{"text":"等的精心策划下进行的。旧剧协在直接出面，具","box":[[2493,1569],[2915,1561],[2915,1587],[2494,1594]]},{"text":"子不是说”一目三省吾身”吗：中国有句老话不是叫“清","box":[[166,1587],[582,1590],[582,1611],[165,1607]]},{"text":"另外加的，不是历史主义地笑山人物。第二是反历史主","box":[[606,1588],[1025,1594],[1025,1614],[606,1608]]},{"text":"倒了，就把大家捆住了。这十条就在作家身上产生","box":[[1046,1580],[1465,1594],[1464,1627],[1045,1613]]},{"text":"的，不管三七二十一就去蛮干的加括弧的“左’","box":[[1594,1594],[2013,1585],[2013,1609],[1594,1618]]},{"text":"很清极的效果，有的同志就成觉得，就是五个一定：一","box":[[1046,1604],[1463,1619],[1462,1648],[1045,1633]]},{"text":"体组织这个黑会的过程中，运用它所谓“社会活","box":[[2493,1595],[2915,1587],[2915,1611],[2494,1619]]},{"text":"夜们心自问”吗：我看这都是自我改造的好方法。另外，","box":[[167,1609],[572,1612],[572,1632],[167,1630]]},{"text":"义，一些语言为了痛快一时，用了一些不恰当的语首，","box":[[606,1611],[1017,1617],[1017,1637],[606,1631]]},{"text":"派，世至胡说“这种人就共所犯错误的后果来","box":[[1589,1621],[2022,1609],[2023,1633],[1590,1645]]},{"text":"在一九六一年六月，圆王殿召集的全国交艺","box":[[2081,1613],[2476,1623],[2475,1647],[2080,1637]]},{"text":"就是多交几个“谭友”。","box":[[166,1631],[347,1632],[346,1653],[165,1651]]},{"text":"定要写重大题材，或者尖增题材。一定要写英人物、","box":[[1045,1626],[1454,1642],[1453,1671],[1044,1655]]},{"text":"动”的方式，充分发挥了这个反革命装多非俱乐部","box":[[2492,1622],[2915,1612],[2915,1636],[2493,1646]]},{"text":"生硬地来影射蒋介石和汉奸。第三强调集体创作，细导","box":[[606,1633],[1023,1638],[1023,1659],[606,1654]]},{"text":"说，和右派差不多，不见得比右派好一点”。他歇斯","box":[[1594,1646],[2023,1636],[2024,1660],[1594,1670]]},{"text":"S","box":[[2027,1646],[2043,1643],[2045,1652],[2029,1656]]},{"text":"工作座谈会上，周扬就居心回测地提出要召开一","box":[[2036,1638],[2477,1647],[2476,1671],[2036,1662]]},{"text":"△一是知识分子本身不是一个阶级，另外，中国的","box":[[199,1651],[582,1654],[582,1678],[199,1675]]},{"text":"演三结合。这三点影响很大。《通上梁山》这出戏说明戏","box":[[605,1655],[1023,1661],[1023,1683],[605,1677]]},{"text":"尖端人物。一定要参加集体创作，就是所谓群众路线。","box":[[1047,1649],[1454,1665],[1453,1694],[1045,1678]]},{"text":"的作用。当时，田汉之流是怎样地得意忘形呵！","box":[[2492,1647],[2903,1638],[2903,1662],[2493,1671]]},{"text":"一定要限期完成。一定要得到领导的批准。作家就有这","box":[[1047,1672],[1461,1688],[1460,1717],[1045,1700]]},{"text":"底里大发作，竞敢运蔑我们伟大领袖毛主席的英","box":[[1594,1671],[2028,1661],[2029,1685],[1594,1695]]},{"text":"次所谓戏剧创作座谈会，图谋从戏剧战线策动牛","box":[[2016,1663],[2474,1673],[2474,1697],[2015,1687]]},{"text":"知识分子确实是革命的。","box":[[168,1675],[354,1677],[354,1697],[168,1696]]},{"text":"曲可以改革，但就这三点没清理，应作典型批判。《戏","box":[[605,1678],[1023,1684],[1023,1704],[605,1698]]},{"text":"当时林默涵亲自出马，赤膊上阵，多次召集旧文","box":[[2493,1674],[2913,1665],[2914,1685],[2494,1695]]},{"text":"△马师合同志从香港回来儿年了，生活水平降低","box":[[201,1697],[587,1701],[587,1722],[200,1719]]},{"text":"样的想法。作家的独创性到那儿去啦？没有啦没有独","box":[[1045,1692],[1464,1710],[1463,1742],[1044,1724]]},{"text":"明领导，胡说什么“反对毛主席，只是反对个人”。","box":[[1595,1696],[2023,1686],[2024,1710],[1596,1720]]},{"text":"鬼蛇神向党进攻。接着，林默涵这个圆王就亲自","box":[[2041,1689],[2473,1698],[2473,1722],[2041,1713]]},{"text":"刚报》有批制它，是漏网之鱼。","box":[[605,1701],[854,1704],[854,1725],[605,1721]]},{"text":"化部和旧剧协的齐燕铭、徐平羽、阳翰笙、赵寻、","box":[[2492,1698],[2910,1688],[2910,1712],[2493,1722]]},{"text":"了，这就是经得佳考验，几次大运动，叉是右倾机会主","box":[[168,1719],[582,1724],[582,1745],[168,1740]]},{"text":"△从长远看来，今天有些求情难看清楚，三面红旗","box":[[641,1723],[1023,1727],[1023,1748],[641,1744]]},{"text":"创性、积极性，他也就不敢写了。","box":[[1048,1722],[1309,1726],[1309,1750],[1048,1746]]},{"text":"他含沙射影地叫靠：“这几年在我们的工作中是","box":[[1595,1721],[2023,1713],[2024,1737],[1595,1745]]},{"text":"布署，派出几路人马，分别到沈阳、哈尔滨、长","box":[[2037,1715],[2477,1725],[2476,1749],[2037,1739]]},{"text":"贺敬之等密谋，并和陶铸勾结一起，经过了这番密","box":[[2495,1724],[2915,1714],[2915,1738],[2495,1748]]},{"text":"义，叉是什么主义，叉没有猪肉吃，叉没有香烟抽，这","box":[[167,1741],[583,1746],[583,1767],[167,1762]]},{"text":"要以后才看得清。","box":[[605,1745],[749,1748],[748,1768],[605,1765]]},{"text":"△谁要是提领导与被领导的矛盾，……就换整，换","box":[[1078,1737],[1464,1754],[1463,1786],[1077,1770]]},{"text":"有不少的缺点和错误的···那个人走路不跌过","box":[[1594,1746],[2022,1739],[2023,1763],[1594,1770]]},{"text":"春、西安、兰州、武汉、广州、桂林、上海、南","box":[[2039,1740],[2478,1749],[2478,1774],[2038,1765]]},{"text":"锣紧鼓，吹吹打打之后，广州黑会宣告开場了。","box":[[2493,1748],[2905,1739],[2905,1763],[2494,1772]]},{"text":"就是考验。","box":[[167,1765],[272,1768],[271,1786],[166,1783]]},{"text":"△那些是该做的，那些是不该做的，受了挫折方能","box":[[637,1768],[1022,1773],[1021,1793],[636,1788]]},{"text":"整面且就是修正主义。","box":[[1047,1769],[1220,1770],[1220,1791],[1047,1789]]},{"text":"子呢？重要的问题是要实事求是地承认缺点和错","box":[[1595,1774],[2025,1765],[2025,1786],[1595,1794]]},{"text":"京、重庆、成都等地，搜索反党材料，纠集党","box":[[2036,1765],[2478,1776],[2477,1800],[2036,1789]]},{"text":"△混滑了政治问题、思想问题、艺术向题或者学术","box":[[1080,1783],[1465,1799],[1464,1832],[1079,1815]]},{"text":"参加这次黑会的有，林默滴、齐燕铭、徐平羽、","box":[[2536,1776],[2912,1765],[2913,1786],[2536,1797]]},{"text":"△最近我在北京看了变盛或的《探阴山》，讲包公怎","box":[[195,1787],[583,1791],[583,1811],[194,1807]]},{"text":"取得经验。这是讲不清楚的，非算正切身体会不可。我","box":[[606,1789],[1024,1796],[1024,1816],[606,1810]]},{"text":"读”。刘少奇狗胆包天，胆敢反对以毛主席为首的","box":[[1596,1798],[2027,1789],[2028,1813],[1597,1822]]},{"text":"羽，对那些受过批判而叉对党心怀怨恨的人，更","box":[[2037,1792],[2480,1800],[2480,1824],[2037,1816]]},{"text":"样替民仲冤，调查研究，大公无私，这很好嘛，但是由","box":[[166,1809],[582,1813],[582,1834],[165,1829]]},{"text":"问题的界线，《洞箫横吹》不是个玫治问题，但要搞成是","box":[[1044,1806],[1465,1822],[1464,1853],[1043,1837]]},{"text":"田汉、阳翰笙、李伯创、张庆、周、老舍、熊佛","box":[[2495,1800],[2916,1789],[2916,1813],[2495,1824]]},{"text":"们兄弟党苏联老大哥跟我们讲也不体会，要自已碰到才","box":[[605,1812],[1022,1818],[1021,1839],[605,1833]]},{"text":"无产阶级司合部，是可忍，就不可忍！","box":[[1596,1824],[1931,1819],[1931,1841],[1597,1846]]},{"text":"是格外看重，大下功夫，这就替广州黑会作出了","box":[[2043,1818],[2483,1827],[2482,1851],[2043,1842]]},{"text":"于它是讲鬼神的，所以过去不能演，这术免太狭窄也太","box":[[164,1831],[582,1836],[582,1857],[164,1852]]},{"text":"西、陈白尘、焦菊隐、马彦群、黄佐临、苏一萍、于黑","box":[[2492,1826],[2916,1814],[2916,1838],[2493,1850]]},{"text":"深刻。","box":[[605,1836],[658,1836],[658,1853],[605,1853]]},{"text":"反党反业会主义，这就错了嘛。","box":[[1048,1837],[1287,1840],[1287,1860],[1048,1858]]},{"text":"在刘少奇的总指挥下，周扬文艺黑帮一个个","box":[[1636,1848],[2024,1842],[2024,1864],[1636,1870]]},{"text":"大量的、细致的舆论上和组织上的准备。","box":[[2041,1842],[2406,1850],[2405,1875],[2041,1867]]},{"text":"简单了。","box":[[162,1857],[229,1857],[229,1873],[162,1873]]},{"text":"△反右倾结果，强迫命合更多，民主空气更少，五","box":[[641,1856],[1022,1863],[1021,1883],[641,1877]]},{"text":"△还要向我们的戏剧传统学习。我们有两个传统，","box":[[1083,1854],[1453,1869],[1452,1897],[1082,1881]]},{"text":"丁、戴碧湘、赵寻、吴雪、金山、孙维世，姚时晓、侣","box":[[2495,1852],[2918,1841],[2919,1865],[2495,1876]]},{"text":"风助长，工业指挥更厉售，这是产生缺点错误的一个","box":[[608,1877],[1023,1886],[1022,1906],[607,1897]]},{"text":"一个元明以来的戏剧传统，另外一个五四以水的传统。","box":[[1054,1874],[1454,1892],[1453,1921],[1053,1903]]},{"text":"披挂上阵，露出一付青面牙，充当了黑司今部","box":[[1596,1873],[2026,1867],[2026,1891],[1597,1897]]},{"text":"在黑会开场之前，周扬在北京亲自纠集一批","box":[[2082,1870],[2480,1877],[2480,1901],[2082,1894]]},{"text":"朋、塞克、海默、于村、刘莲池、岳野、木柯夫、吕西","box":[[2495,1877],[2918,1866],[2919,1890],[2495,1901]]},{"text":"林默涵的黑话","box":[[262,1897],[484,1901],[484,1926],[262,1922]]},{"text":"主婴因素。","box":[[609,1903],[687,1903],[687,1920],[609,1920]]},{"text":"有些作品要背，把它背下来。警如说《寶娥范》","box":[[1061,1897],[1452,1915],[1451,1943],[1060,1926]]},{"text":"下的急先锋。","box":[[1599,1901],[1734,1901],[1734,1921],[1599,1921]]},{"text":"三十年代“老头子”召开了一次小型的黑会，会","box":[[2043,1894],[2482,1902],[2481,1928],[2043,1919]]},{"text":"凡、石凌仙、洛丁、吕复、郑天健、李健吾、王居、","box":[[2491,1902],[2910,1891],[2910,1915],[2492,1926]]},{"text":"△在路指挥下，批评错了一些同志，文化部亦如","box":[[643,1924],[1024,1930],[1024,1950],[642,1944]]},{"text":"《赵氏孤儿》《桃花届》等等这都是好的作品。","box":[[1046,1924],[1391,1935],[1391,1960],[1045,1949]]},{"text":"这年的二月，正是这一小摄反动分子心日中","box":[[1636,1925],[2025,1919],[2025,1940],[1636,1947]]},{"text":"上，他大肆吹捧陶铸，胡说陶铸“作风民主”，广","box":[[2041,1919],[2482,1928],[2481,1953],[2041,1944]]},{"text":"王阁西、周桓、侯甸、李纶、茅盾、贺敬之、张颖、李","box":[[2493,1929],[2921,1916],[2921,1940],[2494,1953]]},{"text":"△人民群众接触文艺，并不是为了去受教育。人们","box":[[198,1942],[583,1945],[583,1966],[198,1962]]},{"text":"此，把张庚同志的学术问题当政治问题来搞。……在这","box":[[606,1944],[1024,1950],[1024,1974],[606,1968]]},{"text":"△谁要是把这一次在我们座谈会上的话，拿去把我","box":[[1081,1942],[1464,1960],[1462,1993],[1079,1975]]},{"text":"的“早春”天气，他们继恶臭惠天的所谓《文艺十","box":[[1596,1950],[2028,1944],[2029,1968],[1597,1974]]},{"text":"东知识分子“心情舒畅”，“那里物质供应好”，主","box":[[2040,1943],[2483,1952],[2482,1979],[2039,1970]]},{"text":"之华、葛一虹、风子、张真等二百余人。","box":[[2492,1954],[2841,1944],[2842,1968],[2493,1978]]},{"text":"总是因为休息娱乐去看看戏吧，看看电影吧。……因此","box":[[161,1964],[582,1967],[582,1989],[161,1986]]},{"text":"种空气下，片面把一切问题搞到政治原则高度，搞得不","box":[[606,1967],[1025,1975],[1025,1996],[606,1987]]},{"text":"们当右倾思想、右派什么来整，我们要给他斗事。你怕","box":[[1044,1965],[1465,1983],[1464,2015],[1043,1998]]},{"text":"条》之后，叉公开扯起“全民文艺”的破旗，紧接","box":[[1597,1977],[2026,1969],[2026,1993],[1598,2001]]},{"text":"张到广州去开黑会。他还别有用心地以医院院长","box":[[2039,1970],[2480,1979],[2480,2003],[2038,1994]]},{"text":"艺术首先要有能引导人的艺术力量。所以对艺术要讲究","box":[[160,1987],[582,1992],[582,2013],[159,2008]]},{"text":"现在看来，广州黑会的反革命气焰所朗那样","box":[[2534,1979],[2919,1965],[2920,1991],[2535,2004]]},{"text":"恰当，一定搞出左右，反党不反党，违反总路线。现在","box":[[604,1991],[1028,1996],[1027,2017],[604,2012]]},{"text":"他干嘛，他要不讲道理嘛，你给他斗。","box":[[1041,1994],[1336,2002],[1335,2026],[1041,2018]]},{"text":"着，一个打着所谓“全国话剧、歌剧，儿童剧创作","box":[[1596,2001],[2029,1997],[2029,2021],[1596,2025]]},{"text":"作不能在手术台旁指挥外科医生，来反对党对创作张，完全是因为有刘、邓、陶等一小摄党内最大","box":[[2010,1995],[2924,1988],[2925,2029],[2011,2035]]},{"text":"座谈会”的幌子，来具体贯彻《文艺十条》这个黑的领导。这就为广州黑会定下了调子，在政治上、的走资本主义道路当权派做后台老板。反革命两","box":[[1590,2017],[2926,2014],[2926,2058],[1590,2062]]},{"text":"本报赣部地址：人民路（原王府大街）38号中国刷协革命造反团","box":[[382,2030],[889,2037],[889,2057],[381,2051]]},{"text":"电话：55.1255","box":[[1128,2039],[1245,2041],[1245,2063],[1128,2060]]},{"text":"钢领的大黑会，就于三月三日在广州开場了。这思想上进行了准备。","box":[[1596,2051],[2222,2047],[2222,2072],[1596,2076]]},{"text":"（下韩第二版）","box":[[2749,2052],[2867,2046],[2868,2067],[2750,2074]]}],"dimensions":{"height":2226,"width":3014}}